Workbook

Sheet Instrucciones
A1: Matriz de validación de descripciones de columnas · SuperApp ESAP · Base completa
A2: Base esap_db (QA) · extracción del 2026-10-22 · generada el 2026-10-22
A4: Objetivo
A5: Revisar con el equipo de desarrollo la descripción de cada columna que aún no tiene descripción registrada en la base ni validada.
A6: Las propuestas se redactaron a partir de la estructura (nombre, tipo, restricciones, valores permitidos, relaciones) y del código de las funciones, triggers y vistas que usan la columna, y del código fuente de la aplicación (entidades y migraciones). No se revisaron valores de los registros. Son propuestas: no reemplazan el conocimiento del equipo.
A8: Cómo revisar (hoja «Matriz»)
A9: 1. Lea la propuesta, su fundamento y, si la hay, la pregunta para desarrollo.
A10: 2. Elija la decisión en la lista desplegable (celdas amarillas):
A11: Aprobada: la propuesta se registra tal cual.
A12: Aprobada con ajuste: escriba el texto correcto en «Descripción final».
A13: Rechazada: la propuesta no corresponde; escriba la descripción correcta en «Descripción final» o explique en «Observaciones».
A14: Requiere aclaración: falta información; anote la duda en «Observaciones».
... A28: Las validadas se publican en el portal y quedan listas para registrarse en la base con un lote COMMENT ON (con reversa), cuando haya autorización.

Sheet Métricas
A1: Métricas de la revisión · Base completa
A3: Avance general
A4: Indicador | B4: Valor
A5: Columnas en la matriz | B5: =COUNTA(Matriz!$A$2:$A$3626) -> 3625
A6: Pendiente | B6: =COUNTIF(Matriz!$V$2:$V$3626,"Pendiente") -> 3625
A7: Aprobada | B7: =COUNTIF(Matriz!$V$2:$V$3626,"Aprobada") -> 0
A8: Aprobada con ajuste | B8: =COUNTIF(Matriz!$V$2:$V$3626,"Aprobada con ajuste") -> 0
A9: Rechazada | B9: =COUNTIF(Matriz!$V$2:$V$3626,"Rechazada") -> 0
A10: Requiere aclaración | B10: =COUNTIF(Matriz!$V$2:$V$3626,"Requiere aclaración") -> 0
A11: Revisadas (decisión distinta de Pendiente) | B11: =B5-B6 -> 0
A12: % revisado | B12: =IF(B5=0,0,B11/B5) -> 0
A13: Con descripción a registrar | B13: =SUMPRODUCT(--(Matriz!$AA$2:$AA$3626<>"")) -> 0
A14: Ajustes sin texto en «Descripción final» | B14: =SUMPRODUCT(((Matriz!$V$2:$V$3626="Aprobada con ajuste")+(Matriz!$V$2:$V$3626="Rechazada"))*(Matriz!$W$2:$W$3626="")) -> 0
A16: Cobertura de descripciones de columnas (indicador K02, meta ≥ 95 %)
A17: Concepto | B17: Valor
A18: Columnas del alcance | B18: 5700
A19: Con descripción registrada en la base (COMMENT) | B19: 604
A20: Validadas antes de esta matriz (config/descripciones.csv) | B20: 1471
A21: Con descripción a registrar en esta matriz | B21: =B13 -> 0
A22: Cobertura actual | B22: =(B19+B20)/B18 -> 0.36403509
A23: Cobertura al incorporar la matriz | B23: =(B19+B20+B21)/B18 -> 0.36403509
A24: Columnas que faltan para la meta de 95 % | B24: =MAX(0,ROUNDUP(0.95*B18,0)-(B19+B20+B21)) -> 3340
A25: Columnas del alcance, base y validadas: cifras fijas de la extracción del 2026-10-22 y de config/descripciones.csv.
A27: Avance por dominio
A28: Dominio | B28: Esquema | C28: Columnas | D28: Aprobadas | E28: Rechazadas | F28: Por aclarar | G28: Pendientes | H28: % revisado
A29: Identidad y acceso | B29: auth | C29: =COUNTIF(Matriz!$C$2:$C$3626,B29) -> 188 | D29: =COUNTIFS(Matriz!$C$2:$C$3626,B29,Matriz!$V$2:$V$3626,"Aprobada")+COUNTIFS(Matriz!$C$2:$C$3626,B29,Matriz!$V$2:$V$3626,"Aprobada con ajuste") -> 0 | E29: =COUNTIFS(Matriz!$C$2:$C$3626,B29,Matriz!$V$2:$V$3626,"Rechazada") -> 0 | F29: =COUNTIFS(Matriz!$C$2:$C$3626,B29,Matriz!$V$2:$V$3626,"Requiere aclaración") -> 0 | G29: =COUNTIFS(Matriz!$C$2:$C$3626,B29,Matriz!$V$2:$V$3626,"Pendiente") -> 188 | H29: =IF(C29=0,0,(C29-G29)/C29) -> 0
A30: Registro académico | B30: academic_registration | C30: =COUNTIF(Matriz!$C$2:$C$3626,B30) -> 124 | D30: =COUNTIFS(Matriz!$C$2:$C$3626,B30,Matriz!$V$2:$V$3626,"Aprobada")+COUNTIFS(Matriz!$C$2:$C$3626,B30,Matriz!$V$2:$V$3626,"Aprobada con ajuste") -> 0 | E30: =COUNTIFS(Matriz!$C$2:$C$3626,B30,Matriz!$V$2:$V$3626,"Rechazada") -> 0 | F30: =COUNTIFS(Matriz!$C$2:$C$3626,B30,Matriz!$V$2:$V$3626,"Requiere aclaración") -> 0 | G30: =COUNTIFS(Matriz!$C$2:$C$3626,B30,Matriz!$V$2:$V$3626,"Pendiente") -> 124 | H30: =IF(C30=0,0,(C30-G30)/C30) -> 0
A31: Plan de trabajo académico | B31: academic_work_plan | C31: =COUNTIF(Matriz!$C$2:$C$3626,B31) -> 512 | D31: =COUNTIFS(Matriz!$C$2:$C$3626,B31,Matriz!$V$2:$V$3626,"Aprobada")+COUNTIFS(Matriz!$C$2:$C$3626,B31,Matriz!$V$2:$V$3626,"Aprobada con ajuste") -> 0 | E31: =COUNTIFS(Matriz!$C$2:$C$3626,B31,Matriz!$V$2:$V$3626,"Rechazada") -> 0 | F31: =COUNTIFS(Matriz!$C$2:$C$3626,B31,Matriz!$V$2:$V$3626,"Requiere aclaración") -> 0 | G31: =COUNTIFS(Matriz!$C$2:$C$3626,B31,Matriz!$V$2:$V$3626,"Pendiente") -> 512 | H31: =IF(C31=0,0,(C31-G31)/C31) -> 0
A32: Certificaciones | B32: certification | C32: =COUNTIF(Matriz!$C$2:$C$3626,B32) -> 107 | D32: =COUNTIFS(Matriz!$C$2:$C$3626,B32,Matriz!$V$2:$V$3626,"Aprobada")+COUNTIFS(Matriz!$C$2:$C$3626,B32,Matriz!$V$2:$V$3626,"Aprobada con ajuste") -> 0 | E32: =COUNTIFS(Matriz!$C$2:$C$3626,B32,Matriz!$V$2:$V$3626,"Rechazada") -> 0 | F32: =COUNTIFS(Matriz!$C$2:$C$3626,B32,Matriz!$V$2:$V$3626,"Requiere aclaración") -> 0 | G32: =COUNTIFS(Matriz!$C$2:$C$3626,B32,Matriz!$V$2:$V$3626,"Pendiente") -> 107 | H32: =IF(C32=0,0,(C32-G32)/C32) -> 0
A33: Gestión jurídica | B33: legal_management | C33: =COUNTIF(Matriz!$C$2:$C$3626,B33) -> 547 | D33: =COUNTIFS(Matriz!$C$2:$C$3626,B33,Matriz!$V$2:$V$3626,"Aprobada")+COUNTIFS(Matriz!$C$2:$C$3626,B33,Matriz!$V$2:$V$3626,"Aprobada con ajuste") -> 0 | E33: =COUNTIFS(Matriz!$C$2:$C$3626,B33,Matriz!$V$2:$V$3626,"Rechazada") -> 0 | F33: =COUNTIFS(Matriz!$C$2:$C$3626,B33,Matriz!$V$2:$V$3626,"Requiere aclaración") -> 0 | G33: =COUNTIFS(Matriz!$C$2:$C$3626,B33,Matriz!$V$2:$V$3626,"Pendiente") -> 547 | H33: =IF(C33=0,0,(C33-G33)/C33) -> 0
A34: Control interno | B34: control_interno | C34: =COUNTIF(Matriz!$C$2:$C$3626,B34) -> 805 | D34: =COUNTIFS(Matriz!$C$2:$C$3626,B34,Matriz!$V$2:$V$3626,"Aprobada")+COUNTIFS(Matriz!$C$2:$C$3626,B34,Matriz!$V$2:$V$3626,"Aprobada con ajuste") -> 0 | E34: =COUNTIFS(Matriz!$C$2:$C$3626,B34,Matriz!$V$2:$V$3626,"Rechazada") -> 0 | F34: =COUNTIFS(Matriz!$C$2:$C$3626,B34,Matriz!$V$2:$V$3626,"Requiere aclaración") -> 0 | G34: =COUNTIFS(Matriz!$C$2:$C$3626,B34,Matriz!$V$2:$V$3626,"Pendiente") -> 805 | H34: =IF(C34=0,0,(C34-G34)/C34) -> 0
A35: Control disciplinario interno | B35: internal_disciplinary_control | C35: =COUNTIF(Matriz!$C$2:$C$3626,B35) -> 206 | D35: =COUNTIFS(Matriz!$C$2:$C$3626,B35,Matriz!$V$2:$V$3626,"Aprobada")+COUNTIFS(Matriz!$C$2:$C$3626,B35,Matriz!$V$2:$V$3626,"Aprobada con ajuste") -> 0 | E35: =COUNTIFS(Matriz!$C$2:$C$3626,B35,Matriz!$V$2:$V$3626,"Rechazada") -> 0 | F35: =COUNTIFS(Matriz!$C$2:$C$3626,B35,Matriz!$V$2:$V$3626,"Requiere aclaración") -> 0 | G35: =COUNTIFS(Matriz!$C$2:$C$3626,B35,Matriz!$V$2:$V$3626,"Pendiente") -> 206 | H35: =IF(C35=0,0,(C35-G35)/C35) -> 0
A36: Requerimientos | B36: requerimientos_oc | C36: =COUNTIF(Matriz!$C$2:$C$3626,B36) -> 70 | D36: =COUNTIFS(Matriz!$C$2:$C$3626,B36,Matriz!$V$2:$V$3626,"Aprobada")+COUNTIFS(Matriz!$C$2:$C$3626,B36,Matriz!$V$2:$V$3626,"Aprobada con ajuste") -> 0 | E36: =COUNTIFS(Matriz!$C$2:$C$3626,B36,Matriz!$V$2:$V$3626,"Rechazada") -> 0 | F36: =COUNTIFS(Matriz!$C$2:$C$3626,B36,Matriz!$V$2:$V$3626,"Requiere aclaración") -> 0 | G36: =COUNTIFS(Matriz!$C$2:$C$3626,B36,Matriz!$V$2:$V$3626,"Pendiente") -> 70 | H36: =IF(C36=0,0,(C36-G36)/C36) -> 0
A37: Notificaciones | B37: notifications | C37: =COUNTIF(Matriz!$C$2:$C$3626,B37) -> 24 | D37: =COUNTIFS(Matriz!$C$2:$C$3626,B37,Matriz!$V$2:$V$3626,"Aprobada")+COUNTIFS(Matriz!$C$2:$C$3626,B37,Matriz!$V$2:$V$3626,"Aprobada con ajuste") -> 0 | E37: =COUNTIFS(Matriz!$C$2:$C$3626,B37,Matriz!$V$2:$V$3626,"Rechazada") -> 0 | F37: =COUNTIFS(Matriz!$C$2:$C$3626,B37,Matriz!$V$2:$V$3626,"Requiere aclaración") -> 0 | G37: =COUNTIFS(Matriz!$C$2:$C$3626,B37,Matriz!$V$2:$V$3626,"Pendiente") -> 24 | H37: =IF(C37=0,0,(C37-G37)/C37) -> 0
A38: Auditoría y trazabilidad | B38: audit | C38: =COUNTIF(Matriz!$C$2:$C$3626,B38) -> 23 | D38: =COUNTIFS(Matriz!$C$2:$C$3626,B38,Matriz!$V$2:$V$3626,"Aprobada")+COUNTIFS(Matriz!$C$2:$C$3626,B38,Matriz!$V$2:$V$3626,"Aprobada con ajuste") -> 0 | E38: =COUNTIFS(Matriz!$C$2:$C$3626,B38,Matriz!$V$2:$V$3626,"Rechazada") -> 0 | F38: =COUNTIFS(Matriz!$C$2:$C$3626,B38,Matriz!$V$2:$V$3626,"Requiere aclaración") -> 0 | G38: =COUNTIFS(Matriz!$C$2:$C$3626,B38,Matriz!$V$2:$V$3626,"Pendiente") -> 23 | H38: =IF(C38=0,0,(C38-G38)/C38) -> 0
A39: Esquema público | B39: public | C39: =COUNTIF(Matriz!$C$2:$C$3626,B39) -> 14 | D39: =COUNTIFS(Matriz!$C$2:$C$3626,B39,Matriz!$V$2:$V$3626,"Aprobada")+COUNTIFS(Matriz!$C$2:$C$3626,B39,Matriz!$V$2:$V$3626,"Aprobada con ajuste") -> 0 | E39: =COUNTIFS(Matriz!$C$2:$C$3626,B39,Matriz!$V$2:$V$3626,"Rechazada") -> 0 | F39: =COUNTIFS(Matriz!$C$2:$C$3626,B39,Matriz!$V$2:$V$3626,"Requiere aclaración") -> 0 | G39: =COUNTIFS(Matriz!$C$2:$C$3626,B39,Matriz!$V$2:$V$3626,"Pendiente") -> 14 | H39: =IF(C39=0,0,(C39-G39)/C39) -> 0
A40: Programación académica | B40: academic-schedule | C40: =COUNTIF(Matriz!$C$2:$C$3626,B40) -> 93 | D40: =COUNTIFS(Matriz!$C$2:$C$3626,B40,Matriz!$V$2:$V$3626,"Aprobada")+COUNTIFS(Matriz!$C$2:$C$3626,B40,Matriz!$V$2:$V$3626,"Aprobada con ajuste") -> 0 | E40: =COUNTIFS(Matriz!$C$2:$C$3626,B40,Matriz!$V$2:$V$3626,"Rechazada") -> 0 | F40: =COUNTIFS(Matriz!$C$2:$C$3626,B40,Matriz!$V$2:$V$3626,"Requiere aclaración") -> 0 | G40: =COUNTIFS(Matriz!$C$2:$C$3626,B40,Matriz!$V$2:$V$3626,"Pendiente") -> 93 | H40: =IF(C40=0,0,(C40-G40)/C40) -> 0
... A44: Asistente virtual (chatbot) | B44: chatbot | C44: =COUNTIF(Matriz!$C$2:$C$3626,B44) -> 16 | D44: =COUNTIFS(Matriz!$C$2:$C$3626,B44,Matriz!$V$2:$V$3626,"Aprobada")+COUNTIFS(Matriz!$C$2:$C$3626,B44,Matriz!$V$2:$V$3626,"Aprobada con ajuste") -> 0 | E44: =COUNTIFS(Matriz!$C$2:$C$3626,B44,Matriz!$V$2:$V$3626,"Rechazada") -> 0 | F44: =COUNTIFS(Matriz!$C$2:$C$3626,B44,Matriz!$V$2:$V$3626,"Requiere aclaración") -> 0 | G44: =COUNTIFS(Matriz!$C$2:$C$3626,B44,Matriz!$V$2:$V$3626,"Pendiente") -> 16 | H44: =IF(C44=0,0,(C44-G44)/C44) -> 0
A45: Total | C45: =SUM(C29:C44) -> 3625 | D45: =SUM(D29:D44) -> 0 | E45: =SUM(E29:E44) -> 0 | F45: =SUM(F29:F44) -> 0 | G45: =SUM(G29:G44) -> 3625 | H45: =IF(C45=0,0,(C45-G45)/C45) -> 0
A47: Avance por confianza y origen de la propuesta
A48: Grupo | B48: Columnas | C48: Aprobadas | D48: Pendientes | E48: % revisado
A49: Confianza Alta | B49: =COUNTIF(Matriz!$S$2:$S$3626,"Alta") -> 1629 | C49: =COUNTIFS(Matriz!$S$2:$S$3626,"Alta",Matriz!$V$2:$V$3626,"Aprobada")+COUNTIFS(Matriz!$S$2:$S$3626,"Alta",Matriz!$V$2:$V$3626,"Aprobada con ajuste") -> 0 | D49: =COUNTIFS(Matriz!$S$2:$S$3626,"Alta",Matriz!$V$2:$V$3626,"Pendiente") -> 1629 | E49: =IF(B49=0,0,(B49-D49)/B49) -> 0
A50: Confianza Media | B50: =COUNTIF(Matriz!$S$2:$S$3626,"Media") -> 1892 | C50: =COUNTIFS(Matriz!$S$2:$S$3626,"Media",Matriz!$V$2:$V$3626,"Aprobada")+COUNTIFS(Matriz!$S$2:$S$3626,"Media",Matriz!$V$2:$V$3626,"Aprobada con ajuste") -> 0 | D50: =COUNTIFS(Matriz!$S$2:$S$3626,"Media",Matriz!$V$2:$V$3626,"Pendiente") -> 1892 | E50: =IF(B50=0,0,(B50-D50)/B50) -> 0
A51: Confianza Baja | B51: =COUNTIF(Matriz!$S$2:$S$3626,"Baja") -> 104 | C51: =COUNTIFS(Matriz!$S$2:$S$3626,"Baja",Matriz!$V$2:$V$3626,"Aprobada")+COUNTIFS(Matriz!$S$2:$S$3626,"Baja",Matriz!$V$2:$V$3626,"Aprobada con ajuste") -> 0 | D51: =COUNTIFS(Matriz!$S$2:$S$3626,"Baja",Matriz!$V$2:$V$3626,"Pendiente") -> 104 | E51: =IF(B51=0,0,(B51-D51)/B51) -> 0
A52: Origen: Código fuente | B52: =COUNTIF(Matriz!$Q$2:$Q$3626,"Código fuente") -> 866 | C52: =COUNTIFS(Matriz!$Q$2:$Q$3626,"Código fuente",Matriz!$V$2:$V$3626,"Aprobada")+COUNTIFS(Matriz!$Q$2:$Q$3626,"Código fuente",Matriz!$V$2:$V$3626,"Aprobada con ajuste") -> 0 | D52: =COUNTIFS(Matriz!$Q$2:$Q$3626,"Código fuente",Matriz!$V$2:$V$3626,"Pendiente") -> 866 | E52: =IF(B52=0,0,(B52-D52)/B52) -> 0
A53: Origen: Regla estructural | B53: =COUNTIF(Matriz!$Q$2:$Q$3626,"Regla estructural") -> 1047 | C53: =COUNTIFS(Matriz!$Q$2:$Q$3626,"Regla estructural",Matriz!$V$2:$V$3626,"Aprobada")+COUNTIFS(Matriz!$Q$2:$Q$3626,"Regla estructural",Matriz!$V$2:$V$3626,"Aprobada con ajuste") -> 0 | D53: =COUNTIFS(Matriz!$Q$2:$Q$3626,"Regla estructural",Matriz!$V$2:$V$3626,"Pendiente") -> 1047 | E53: =IF(B53=0,0,(B53-D53)/B53) -> 0
A54: Origen: Propuesta semántica | B54: =COUNTIF(Matriz!$Q$2:$Q$3626,"Propuesta semántica") -> 1712 | C54: =COUNTIFS(Matriz!$Q$2:$Q$3626,"Propuesta semántica",Matriz!$V$2:$V$3626,"Aprobada")+COUNTIFS(Matriz!$Q$2:$Q$3626,"Propuesta semántica",Matriz!$V$2:$V$3626,"Aprobada con ajuste") -> 0 | D54: =COUNTIFS(Matriz!$Q$2:$Q$3626,"Propuesta semántica",Matriz!$V$2:$V$3626,"Pendiente") -> 1712 | E54: =IF(B54=0,0,(B54-D54)/B54) -> 0
A55: Con evidencia en código | B55: =COUNTIF(Matriz!$P$2:$P$3626,"?*") -> 2941 | C55: =COUNTIFS(Matriz!$P$2:$P$3626,"?*",Matriz!$V$2:$V$3626,"Aprobada")+COUNTIFS(Matriz!$P$2:$P$3626,"?*",Matriz!$V$2:$V$3626,"Aprobada con ajuste") -> 0 | D55: =COUNTIFS(Matriz!$P$2:$P$3626,"?*",Matriz!$V$2:$V$3626,"Pendiente") -> 2941 | E55: =IF(B55=0,0,(B55-D55)/B55) -> 0
A56: Usadas en lógica de la base | B56: =COUNTIF(Matriz!$M$2:$M$3626,"Sí") -> 142 | C56: =COUNTIFS(Matriz!$M$2:$M$3626,"Sí",Matriz!$V$2:$V$3626,"Aprobada")+COUNTIFS(Matriz!$M$2:$M$3626,"Sí",Matriz!$V$2:$V$3626,"Aprobada con ajuste") -> 0 | D56: =COUNTIFS(Matriz!$M$2:$M$3626,"Sí",Matriz!$V$2:$V$3626,"Pendiente") -> 142 | E56: =IF(B56=0,0,(B56-D56)/B56) -> 0
A57: Relacionadas con catálogo | B57: =COUNTIF(Matriz!$L$2:$L$3626,"Sí") -> 388 | C57: =COUNTIFS(Matriz!$L$2:$L$3626,"Sí",Matriz!$V$2:$V$3626,"Aprobada")+COUNTIFS(Matriz!$L$2:$L$3626,"Sí",Matriz!$V$2:$V$3626,"Aprobada con ajuste") -> 0 | D57: =COUNTIFS(Matriz!$L$2:$L$3626,"Sí",Matriz!$V$2:$V$3626,"Pendiente") -> 388 | E57: =IF(B57=0,0,(B57-D57)/B57) -> 0

Sheet Matriz
A1: ID | B1: Dominio | C1: Esquema | D1: Tabla | E1: Filas en QA | F1: Columna | G1: Tipo de dato | H1: Admite nulos | I1: Restricciones | J1: Valores permitidos | K1: Referencia (FK) | L1: Catálogo | M1: Uso en lógica | N1: Detalle del uso | O1: Índices | P1: Evidencia en código | Q1: Origen | R1: Propuesta de descripción | S1: Confianza | T1: Fundamento | U1: Pregunta para desarrollo | V1: Decisión | W1: Descripción final | X1: Revisado por | Y1: Fecha de revisión | Z1: Observaciones | AA1: Descripción a registrar
A2: C0001 | B2: Identidad y acceso | C2: auth | D2: acreditaciones_programa | E2: 5 | F2: tipo | G2: text | H2: No | L2: No | M2: No | P2: db/migrations/old/006_create_programas_academicos.sql:49: Alta Calidad, Internacional, etc. | Q2: Código fuente | R2: Tipo de acreditación del programa académico (por ejemplo, Alta Calidad, Internacional). | S2: Alta | T2: código: db/migrations/old/006_create_programas_academicos.sql:49 | V2: Pendiente | AA2: =IF(OR(V2="Aprobada"),R2,IF(AND(OR(V2="Aprobada con ajuste",V2="Rechazada"),W2<>""),W2,""))
A3: C0002 | B3: Identidad y acceso | C3: auth | D3: acreditaciones_programa | E3: 5 | F3: vigencia | G3: date | H3: No | L3: No | M3: No | Q3: Regla estructural | R3: Vigencia (año). | S3: Media | T3: Convención de nombre de la columna. | V3: Pendiente | AA3: =IF(OR(V3="Aprobada"),R3,IF(AND(OR(V3="Aprobada con ajuste",V3="Rechazada"),W3<>""),W3,""))
A4: C0003 | B4: Identidad y acceso | C4: auth | D4: cargos | E4: 17 | F4: cod_cargo | G4: character varying(50) | H4: No | I4: Única | L4: No | M4: No | O4: cargos_cod_cargo_key, idx_cargos_codigo | P4: Mapeada en auth-service/src/users/cargo.entity.ts:19 (Cargo.codCargo) | Validación: IsString, MaxLength(50, { message: 'El código de cargo no puede exceder 50 caracteres' }) | Q4: Propuesta semántica | R4: Código del cargo; es único en la tabla (máximo 50 caracteres). | S4: Alta | T4: nombre + tipo + columnas vecinas + restricción única + validaciones | V4: Pendiente | AA4: =IF(OR(V4="Aprobada"),R4,IF(AND(OR(V4="Aprobada con ajuste",V4="Rechazada"),W4<>""),W4,""))
A5: C0004 | B5: Identidad y acceso | C5: auth | D5: cargos | E5: 17 | F5: nom_cargo | G5: character varying(250) | H5: No | L5: No | M5: No | O5: idx_cargos_nombre | P5: Mapeada en auth-service/src/users/cargo.entity.ts:22 (Cargo.nomCargo) | Validación: IsString, MaxLength(250, { message: 'El nombre de cargo no puede exceder 250 caracteres' }) | Q5: Propuesta semántica | R5: Nombre del cargo (máximo 250 caracteres). | S5: Alta | T5: nombre + tipo + columnas vecinas + validaciones | V5: Pendiente | AA5: =IF(OR(V5="Aprobada"),R5,IF(AND(OR(V5="Aprobada con ajuste",V5="Rechazada"),W5<>""),W5,""))
A6: C0005 | B6: Identidad y acceso | C6: auth | D6: cargos | E6: 17 | F6: descripcion | G6: character varying(500) | H6: Sí | L6: No | M6: No | P6: Mapeada en auth-service/src/users/cargo.entity.ts:25 (Cargo.descripcion) | Validación: IsOptional, IsString, MaxLength(150), MaxLength(150, { message: 'La descripción no puede superar 150 caracteres' }), MaxLength(500) | Q6: Regla estructural | R6: Descripción del registro de cargos. | S6: Media | T6: Convención de nombre de la columna. | V6: Pendiente | AA6: =IF(OR(V6="Aprobada"),R6,IF(AND(OR(V6="Aprobada con ajuste",V6="Rechazada"),W6<>""),W6,""))
A7: C0006 | B7: Identidad y acceso | C7: auth | D7: cargos | E7: 17 | F7: nivel_jerarquico | G7: character varying(50) | H7: Sí | L7: No | M7: No | P7: Mapeada en auth-service/src/users/cargo.entity.ts:28 (Cargo.nivelJerarquico) | Validación: IsOptional, IsString, MaxLength(50) | Q7: Propuesta semántica | R7: Nivel jerárquico del cargo. Por defecto, Profesional. | S7: Media | T7: nombre + tipo + columnas vecinas + defecto | U7: ¿Qué valores toma el nivel jerárquico (Directivo, Asesor, Profesional, Técnico, Asistencial)? | V7: Pendiente | AA7: =IF(OR(V7="Aprobada"),R7,IF(AND(OR(V7="Aprobada con ajuste",V7="Rechazada"),W7<>""),W7,""))
A8: C0007 | B8: Identidad y acceso | C8: auth | D8: cargos | E8: 17 | F8: activo | G8: boolean | H8: No | L8: No | M8: No | O8: idx_cargos_activo | P8: Mapeada en auth-service/src/users/cargo.entity.ts:36 (Cargo.activo) | Validación: IsBoolean, IsOptional | Q8: Regla estructural | R8: Indica si el registro está activo. | S8: Media | T8: Convención de nombre de la columna. | V8: Pendiente | AA8: =IF(OR(V8="Aprobada"),R8,IF(AND(OR(V8="Aprobada con ajuste",V8="Rechazada"),W8<>""),W8,""))
A9: C0008 | B9: Identidad y acceso | C9: auth | D9: carpeta_digital | E9: 409 | F9: nombre_carpeta | G9: character varying(255) | H9: Sí | L9: No | M9: No | P9: Mapeada en auth-service/src/carpeta-digital/carpeta-digital.entity.ts:24 (CarpetaDigital.nombreCarpeta) | Q9: Propuesta semántica | R9: Nombre de la carpeta digital de la persona. | S9: Alta | T9: nombre + tipo + columnas vecinas | V9: Pendiente | AA9: =IF(OR(V9="Aprobada"),R9,IF(AND(OR(V9="Aprobada con ajuste",V9="Rechazada"),W9<>""),W9,""))
A10: C0009 | B10: Identidad y acceso | C10: auth | D10: carpeta_digital | E10: 409 | F10: estado | G10: character varying(30) | H10: No | L10: No | M10: No | O10: idx_carpeta_digital_estado | P10: Mapeada en auth-service/src/carpeta-digital/carpeta-digital.entity.ts:27 (CarpetaDigital.estado) | Validación: IsOptional, IsString | Q10: Regla estructural | R10: Estado del registro de carpeta_digital. | S10: Media | T10: Convención de nombre de la columna. | V10: Pendiente | AA10: =IF(OR(V10="Aprobada"),R10,IF(AND(OR(V10="Aprobada con ajuste",V10="Rechazada"),W10<>""),W10,""))
A11: C0010 | B11: Identidad y acceso | C11: auth | D11: carpeta_digital | E11: 409 | F11: metadata | G11: jsonb | H11: Sí | L11: No | M11: No | P11: Mapeada en auth-service/src/carpeta-digital/carpeta-digital.entity.ts:30 (CarpetaDigital.metadata) | Q11: Regla estructural | R11: Metadatos adicionales en formato JSON. | S11: Media | T11: Convención de nombre de la columna. | V11: Pendiente | AA11: =IF(OR(V11="Aprobada"),R11,IF(AND(OR(V11="Aprobada con ajuste",V11="Rechazada"),W11<>""),W11,""))
A12: C0011 | B12: Identidad y acceso | C12: auth | D12: dependencias | E12: 7 | F12: id_empresa | G12: numeric(11,0) | H12: No | L12: No | M12: No | P12: Mapeada en auth-service/src/users/dependencia.entity.ts:52 (Dependencia.idEmpresa) | Q12: Propuesta semántica | R12: Identificador de la empresa o entidad a la que pertenece la dependencia. Por defecto, 1. | S12: Media | T12: nombre + tipo + columnas vecinas + documentación de la entidad | U12: ¿Qué tabla identifica id_empresa y hay más de una empresa registrada? | V12: Pendiente | AA12: =IF(OR(V12="Aprobada"),R12,IF(AND(OR(V12="Aprobada con ajuste",V12="Rechazada"),W12<>""),W12,""))
A13: C0012 | B13: Identidad y acceso | C13: auth | D13: dependencias | E13: 7 | F13: cod_dependencia | G13: character varying(20) | H13: No | I13: Única | L13: No | M13: No | O13: dependencias_cod_dependencia_key | P13: Mapeada en auth-service/src/users/dependencia.entity.ts:55 (Dependencia.codDependencia) | Validación: IsOptional, IsString, MaxLength(20), MaxLength(20, { message: 'El código de dependencia no puede exceder 20 caracteres' }) | Q13: Propuesta semántica | R13: Código de la dependencia; es único en la tabla (máximo 20 caracteres). | S13: Alta | T13: nombre + tipo + columnas vecinas + restricción única + validaciones | V13: Pendiente | AA13: =IF(OR(V13="Aprobada"),R13,IF(AND(OR(V13="Aprobada con ajuste",V13="Rechazada"),W13<>""),W13,""))
A14: C0013 | B14: Identidad y acceso | C14: auth | D14: dependencias | E14: 7 | F14: nom_dependencia | G14: character varying(250) | H14: No | L14: No | M14: No | P14: Mapeada en auth-service/src/users/dependencia.entity.ts:58 (Dependencia.nomDependencia) | Validación: IsOptional, IsString, MaxLength(250), MaxLength(250, { message: 'El nombre de dependencia no puede exceder 250 caracteres' }) | Q14: Propuesta semántica | R14: Nombre de la dependencia (máximo 250 caracteres). | S14: Alta | T14: nombre + tipo + columnas vecinas + validaciones | V14: Pendiente | AA14: =IF(OR(V14="Aprobada"),R14,IF(AND(OR(V14="Aprobada con ajuste",V14="Rechazada"),W14<>""),W14,""))
A15: C0014 | B15: Identidad y acceso | C15: auth | D15: dependencias | E15: 7 | F15: dir_dependencia | G15: character varying(250) | H15: Sí | L15: No | M15: No | P15: Mapeada en auth-service/src/users/dependencia.entity.ts:61 (Dependencia.dirDependencia) | Validación: IsOptional, IsString, MaxLength(250) | Q15: Propuesta semántica | R15: Dirección física de la dependencia. | S15: Media | T15: nombre + tipo + columnas vecinas (dir_email, url_dependencia) | U15: ¿dir_dependencia es la dirección postal de la dependencia? | V15: Pendiente | AA15: =IF(OR(V15="Aprobada"),R15,IF(AND(OR(V15="Aprobada con ajuste",V15="Rechazada"),W15<>""),W15,""))
A16: C0015 | B16: Identidad y acceso | C16: auth | D16: dependencias | E16: 7 | F16: dir_email | G16: character varying(250) | H16: Sí | L16: No | M16: No | P16: Mapeada en auth-service/src/users/dependencia.entity.ts:64 (Dependencia.dirEmail) | Validación: IsEmail, IsEmail({}, { message: 'El email institucional no es válido' }), IsOptional, MaxLength(250) | Q16: Propuesta semántica | R16: Correo electrónico institucional de la dependencia. | S16: Alta | T16: nombre + tipo + columnas vecinas + validación IsEmail | V16: Pendiente | AA16: =IF(OR(V16="Aprobada"),R16,IF(AND(OR(V16="Aprobada con ajuste",V16="Rechazada"),W16<>""),W16,""))
A17: C0016 | B17: Identidad y acceso | C17: auth | D17: dependencias | E17: 7 | F17: url_dependencia | G17: character varying(250) | H17: Sí | L17: No | M17: No | P17: Mapeada en auth-service/src/users/dependencia.entity.ts:67 (Dependencia.urlDependencia) | Validación: IsOptional, IsString, MaxLength(250) | Q17: Propuesta semántica | R17: Dirección web (URL) de la dependencia. | S17: Alta | T17: nombre + tipo + columnas vecinas | V17: Pendiente | AA17: =IF(OR(V17="Aprobada"),R17,IF(AND(OR(V17="Aprobada con ajuste",V17="Rechazada"),W17<>""),W17,""))
A18: C0017 | B18: Identidad y acceso | C18: auth | D18: dependencias | E18: 7 | F18: id_geopolitica | G18: numeric(11,0) | H18: Sí | L18: No | M18: No | P18: Mapeada en auth-service/src/users/dependencia.entity.ts:70 (Dependencia.idGeopolitica) | Validación: IsNumber, IsOptional | Q18: Propuesta semántica | R18: Identificador de la división geopolítica (ciudad o municipio) donde se ubica la dependencia. | S18: Media | T18: nombre + tipo + columnas vecinas (auth.geopolitica) | U18: ¿id_geopolitica referencia a auth.geopolitica.id_geopolitica? | V18: Pendiente | AA18: =IF(OR(V18="Aprobada"),R18,IF(AND(OR(V18="Aprobada con ajuste",V18="Rechazada"),W18<>""),W18,""))
A19: C0018 | B19: Identidad y acceso | C19: auth | D19: dependencias | E19: 7 | F19: id_sede | G19: numeric(11,0) | H19: Sí | L19: No | M19: No | P19: Mapeada en auth-service/src/users/dependencia.entity.ts:73 (Dependencia.idSede) | Validación: IsNumber, IsOptional | Q19: Regla estructural | R19: Referencia al registro de auth.sedes (id_sede); relación sin llave foránea declarada. | S19: Media | T19: Convención de nombre de la columna. | V19: Pendiente | AA19: =IF(OR(V19="Aprobada"),R19,IF(AND(OR(V19="Aprobada con ajuste",V19="Rechazada"),W19<>""),W19,""))
A20: C0019 | B20: Identidad y acceso | C20: auth | D20: dependencias | E20: 7 | F20: id_cargo | G20: numeric(11,0) | H20: Sí | L20: No | M20: No | P20: Mapeada en auth-service/src/users/dependencia.entity.ts:76 (Dependencia.idCargo) | Validación: IsNumber, IsOptional | Q20: Propuesta semántica | R20: Identificador del cargo asociado a la dependencia. | S20: Baja | T20: nombre + tipo + columnas vecinas (auth.cargos) | U20: ¿id_cargo es el cargo del jefe de la dependencia? ¿Referencia a auth.cargos? | V20: Pendiente | AA20: =IF(OR(V20="Aprobada"),R20,IF(AND(OR(V20="Aprobada con ajuste",V20="Rechazada"),W20<>""),W20,""))
A21: C0020 | B21: Identidad y acceso | C21: auth | D21: dependencias | E21: 7 | F21: id_tercero | G21: numeric(11,0) | H21: Sí | L21: No | M21: No | P21: Mapeada en auth-service/src/users/dependencia.entity.ts:79 (Dependencia.idTercero) | Validación: IsNumber, IsOptional | Q21: Propuesta semántica | R21: Identificador del tercero asociado a la dependencia. | S21: Baja | T21: nombre + tipo + columnas vecinas | U21: ¿Qué representa el tercero (responsable de la dependencia) y a qué tabla referencia? | V21: Pendiente | AA21: =IF(OR(V21="Aprobada"),R21,IF(AND(OR(V21="Aprobada con ajuste",V21="Rechazada"),W21<>""),W21,""))
A22: C0021 | B22: Identidad y acceso | C22: auth | D22: dependencias | E22: 7 | F22: tip_unidad | G22: numeric(1,0) | H22: Sí | L22: No | M22: No | P22: Mapeada en auth-service/src/users/dependencia.entity.ts:82 (Dependencia.tipUnidad) | Validación: IsNumber, IsOptional | Q22: Propuesta semántica | R22: Código del tipo de unidad organizacional de la dependencia. | S22: Baja | T22: nombre + tipo + columnas vecinas (gen_tip_unidad) | U22: ¿Qué valores toma tip_unidad y qué significa cada uno? | V22: Pendiente | AA22: =IF(OR(V22="Aprobada"),R22,IF(AND(OR(V22="Aprobada con ajuste",V22="Rechazada"),W22<>""),W22,""))
A23: C0022 | B23: Identidad y acceso | C23: auth | D23: dependencias | E23: 7 | F23: gen_tip_unidad | G23: character varying(6) | H23: Sí | L23: No | M23: No | P23: Mapeada en auth-service/src/users/dependencia.entity.ts:85 (Dependencia.genTipUnidad) | Validación: IsOptional, IsString, MaxLength(6) | Q23: Propuesta semántica | R23: Código del grupo de parámetros que define los tipos de unidad. Por defecto, TIUORG (tipo de unidad organizacional). | S23: Baja | T23: nombre + tipo + columnas vecinas + defecto | U23: ¿gen_tip_unidad es el código de la lista genérica a la que pertenece tip_unidad? | V23: Pendiente | AA23: =IF(OR(V23="Aprobada"),R23,IF(AND(OR(V23="Aprobada con ajuste",V23="Rechazada"),W23<>""),W23,""))
A24: C0023 | B24: Identidad y acceso | C24: auth | D24: dependencias | E24: 7 | F24: descripcion | G24: character varying(500) | H24: Sí | L24: No | M24: No | P24: Mapeada en auth-service/src/users/dependencia.entity.ts:88 (Dependencia.descripcion) | Validación: IsOptional, IsString, MaxLength(150), MaxLength(150, { message: 'La descripción no puede superar 150 caracteres' }), MaxLength(500) | Q24: Regla estructural | R24: Descripción del registro de dependencias. | S24: Media | T24: Convención de nombre de la columna. | V24: Pendiente | AA24: =IF(OR(V24="Aprobada"),R24,IF(AND(OR(V24="Aprobada con ajuste",V24="Rechazada"),W24<>""),W24,""))
A25: C0024 | B25: Identidad y acceso | C25: auth | D25: dependencias | E25: 7 | F25: activo | G25: boolean | H25: No | L25: No | M25: No | O25: idx_dependencias_activo | P25: Mapeada en auth-service/src/users/dependencia.entity.ts:91 (Dependencia.activo) | Validación: IsBoolean, IsOptional | Q25: Regla estructural | R25: Indica si el registro está activo. | S25: Media | T25: Convención de nombre de la columna. | V25: Pendiente | AA25: =IF(OR(V25="Aprobada"),R25,IF(AND(OR(V25="Aprobada con ajuste",V25="Rechazada"),W25<>""),W25,""))
A26: C0025 | B26: Identidad y acceso | C26: auth | D26: dependencias_cargos | E26: 30 | F26: activo | G26: boolean | H26: No | L26: No | M26: No | O26: idx_dep_cargos_activo | P26: Mapeada en auth-service/src/users/dependencia-cargo.entity.ts:29 (DependenciaCargo.activo) | Validación: IsBoolean, IsOptional | Q26: Regla estructural | R26: Indica si el registro está activo. | S26: Media | T26: Convención de nombre de la columna. | V26: Pendiente | AA26: =IF(OR(V26="Aprobada"),R26,IF(AND(OR(V26="Aprobada con ajuste",V26="Rechazada"),W26<>""),W26,""))
A27: C0026 | B27: Identidad y acceso | C27: auth | D27: documento_carpeta_digital | E27: 0 | F27: nombre | G27: character varying(255) | H27: No | L27: No | M27: No | P27: db/migrations/339_create_documento_carpeta_digital.sql:29: Metadatos del archivo | Validación: IsOptional, IsString | Q27: Código fuente | R27: Nombre del archivo del documento cargado en la Carpeta Digital. | S27: Media | T27: código: db/migrations/339_create_documento_carpeta_digital.sql:29 | U27: ¿nombre guarda el nombre original del archivo o un nombre descriptivo del documento? | V27: Pendiente | AA27: =IF(OR(V27="Aprobada"),R27,IF(AND(OR(V27="Aprobada con ajuste",V27="Rechazada"),W27<>""),W27,""))
A28: C0027 | B28: Identidad y acceso | C28: auth | D28: documento_carpeta_digital | E28: 0 | F28: categoria | G28: character varying(80) | H28: No | L28: No | M28: No | P28: Mapeada en auth-service/src/carpeta-digital/documento-carpeta-digital.entity.ts:43 (DocumentoCarpetaDigital.categoria) | Q28: Propuesta semántica | R28: Categoría del documento en la carpeta digital. Por defecto, otros. | S28: Media | T28: nombre + tipo + columnas vecinas + defecto | U28: ¿Qué categorías se usan y de qué catálogo provienen? | V28: Pendiente | AA28: =IF(OR(V28="Aprobada"),R28,IF(AND(OR(V28="Aprobada con ajuste",V28="Rechazada"),W28<>""),W28,""))
A29: C0028 | B29: Identidad y acceso | C29: auth | D29: documento_carpeta_digital | E29: 0 | F29: tipo_archivo | G29: character varying(40) | H29: Sí | L29: No | M29: No | P29: Mapeada en auth-service/src/carpeta-digital/documento-carpeta-digital.entity.ts:46 (DocumentoCarpetaDigital.tipoArchivo) | Q29: Propuesta semántica | R29: Tipo o formato del archivo subido (por ejemplo, pdf). | S29: Media | T29: nombre + tipo + columnas vecinas | U29: ¿Se guarda la extensión o el tipo MIME del archivo? | V29: Pendiente | AA29: =IF(OR(V29="Aprobada"),R29,IF(AND(OR(V29="Aprobada con ajuste",V29="Rechazada"),W29<>""),W29,""))
A30: C0029 | B30: Identidad y acceso | C30: auth | D30: documento_carpeta_digital | E30: 0 | F30: tamano_bytes | G30: bigint | H30: Sí | L30: No | M30: No | P30: Mapeada en auth-service/src/carpeta-digital/documento-carpeta-digital.entity.ts:49 (DocumentoCarpetaDigital.tamanoBytes) | Q30: Regla estructural | R30: Tamaño del archivo en bytes. | S30: Media | T30: Convención de nombre de la columna. | V30: Pendiente | AA30: =IF(OR(V30="Aprobada"),R30,IF(AND(OR(V30="Aprobada con ajuste",V30="Rechazada"),W30<>""),W30,""))
A31: C0030 | B31: Identidad y acceso | C31: auth | D31: documento_carpeta_digital | E31: 0 | F31: estado | G31: character varying(30) | H31: No | I31: CHECK | J31: pendiente, rechazado, validado, vencido | L31: Sí | M31: No | O31: idx_documento_cd_estado | P31: db/migrations/339_create_documento_carpeta_digital.sql:36: Estado de validación | Validación: IsOptional, IsString | Q31: Código fuente | R31: Estado de validación del documento. Valores permitidos: pendiente, validado, rechazado, vencido; por defecto pendiente. | S31: Alta | T31: código: db/migrations/339_create_documento_carpeta_digital.sql:36 | V31: Pendiente | AA31: =IF(OR(V31="Aprobada"),R31,IF(AND(OR(V31="Aprobada con ajuste",V31="Rechazada"),W31<>""),W31,""))
A32: C0031 | B32: Identidad y acceso | C32: auth | D32: documento_carpeta_digital | E32: 0 | F32: comentarios | G32: text | H32: Sí | L32: No | M32: No | P32: Mapeada en auth-service/src/carpeta-digital/documento-carpeta-digital.entity.ts:58 (DocumentoCarpetaDigital.comentarios) | Q32: Propuesta semántica | R32: Comentarios sobre el documento, como observaciones de la validación. | S32: Media | T32: nombre + tipo + columnas vecinas (estado, validado_por) | U32: ¿Los comentarios los escribe quien valida, quien sube el documento o ambos? | V32: Pendiente | AA32: =IF(OR(V32="Aprobada"),R32,IF(AND(OR(V32="Aprobada con ajuste",V32="Rechazada"),W32<>""),W32,""))
A33: C0032 | B33: Identidad y acceso | C33: auth | D33: documento_carpeta_digital | E33: 0 | F33: validado_por | G33: uuid | H33: Sí | L33: No | M33: No | P33: Mapeada en auth-service/src/carpeta-digital/documento-carpeta-digital.entity.ts:61 (DocumentoCarpetaDigital.validadoPor) | Q33: Regla estructural | R33: Usuario que realizó la validación. | S33: Media | T33: Convención de nombre de la columna. | V33: Pendiente | AA33: =IF(OR(V33="Aprobada"),R33,IF(AND(OR(V33="Aprobada con ajuste",V33="Rechazada"),W33<>""),W33,""))
A34: C0033 | B34: Identidad y acceso | C34: auth | D34: documento_carpeta_digital | E34: 0 | F34: fecha_validacion | G34: timestamp without time zone | H34: Sí | L34: No | M34: No | P34: Mapeada en auth-service/src/carpeta-digital/documento-carpeta-digital.entity.ts:64 (DocumentoCarpetaDigital.fechaValidacion) | Q34: Regla estructural | R34: Fecha de validación. | S34: Media | T34: Convención de nombre de la columna. | V34: Pendiente | AA34: =IF(OR(V34="Aprobada"),R34,IF(AND(OR(V34="Aprobada con ajuste",V34="Rechazada"),W34<>""),W34,""))
A35: C0034 | B35: Identidad y acceso | C35: auth | D35: documento_carpeta_digital | E35: 0 | F35: fecha_subida | G35: timestamp without time zone | H35: No | L35: No | M35: No | P35: db/migrations/339_create_documento_carpeta_digital.sql:42: Fechas | Q35: Código fuente | R35: Fecha y hora en que la persona cargó el documento; por defecto el momento de creación. | S35: Alta | T35: código: db/migrations/339_create_documento_carpeta_digital.sql:42 | V35: Pendiente | AA35: =IF(OR(V35="Aprobada"),R35,IF(AND(OR(V35="Aprobada con ajuste",V35="Rechazada"),W35<>""),W35,""))
A36: C0035 | B36: Identidad y acceso | C36: auth | D36: documento_carpeta_digital | E36: 0 | F36: fecha_vencimiento | G36: timestamp without time zone | H36: Sí | L36: No | M36: No | P36: Mapeada en auth-service/src/carpeta-digital/documento-carpeta-digital.entity.ts:70 (DocumentoCarpetaDigital.fechaVencimiento) | Q36: Regla estructural | R36: Fecha de vencimiento. | S36: Media | T36: Convención de nombre de la columna. | V36: Pendiente | AA36: =IF(OR(V36="Aprobada"),R36,IF(AND(OR(V36="Aprobada con ajuste",V36="Rechazada"),W36<>""),W36,""))
A37: C0036 | B37: Identidad y acceso | C37: auth | D37: festivos_colombia | E37: 18 | F37: fecha | G37: date | H37: No | I37: Única | L37: No | M37: No | O37: festivos_colombia_fecha_key, idx_auth_festivos_fecha | P37: Mapeada en travel-expenses-service/src/entities/festivo-colombia.entity.ts:21 (FestivoColombiaEntity.fecha) | Q37: Propuesta semántica | R37: Fecha del día festivo; es única en la tabla. | S37: Alta | T37: documentación de la entidad + restricción única | V37: Pendiente | AA37: =IF(OR(V37="Aprobada"),R37,IF(AND(OR(V37="Aprobada con ajuste",V37="Rechazada"),W37<>""),W37,""))
A38: C0037 | B38: Identidad y acceso | C38: auth | D38: festivos_colombia | E38: 18 | F38: descripcion | G38: character varying(150) | H38: No | L38: No | M38: No | P38: Mapeada en travel-expenses-service/src/entities/festivo-colombia.entity.ts:24 (FestivoColombiaEntity.descripcion) | Validación: IsOptional, IsString, Length(0, 255) | Q38: Regla estructural | R38: Descripción del registro de festivos_colombia. | S38: Media | T38: Convención de nombre de la columna. | V38: Pendiente | AA38: =IF(OR(V38="Aprobada"),R38,IF(AND(OR(V38="Aprobada con ajuste",V38="Rechazada"),W38<>""),W38,""))
A39: C0038 | B39: Identidad y acceso | C39: auth | D39: festivos_colombia | E39: 18 | F39: origen | G39: character varying(150) | H39: Sí | L39: No | M39: No | P39: Mapeada en auth-service/src/settings/festivo-colombia.entity.ts:26 (FestivoColombia.origen) | Validación: IsOptional, IsString, MaxLength(150) | Q39: Propuesta semántica | R39: Norma que establece el festivo. Por defecto, Ley 51/1983. | S39: Media | T39: nombre + tipo + columnas vecinas + defecto | U39: ¿origen guarda siempre la norma legal o también la fuente de carga? | V39: Pendiente | AA39: =IF(OR(V39="Aprobada"),R39,IF(AND(OR(V39="Aprobada con ajuste",V39="Rechazada"),W39<>""),W39,""))
A40: C0039 | B40: Identidad y acceso | C40: auth | D40: festivos_colombia | E40: 18 | F40: regla | G40: character varying(50) | H40: Sí | L40: No | M40: No | P40: Mapeada en auth-service/src/settings/festivo-colombia.entity.ts:35 (FestivoColombia.regla) | Validación: IsOptional, IsString, MaxLength(50) | Q40: Propuesta semántica | R40: Regla con la que se determina la fecha del festivo. Por defecto, fixed (fecha fija). | S40: Media | T40: nombre + tipo + columnas vecinas + defecto | U40: ¿Qué otros valores toma regla (por ejemplo, traslado al lunes o basado en Pascua)? | V40: Pendiente | AA40: =IF(OR(V40="Aprobada"),R40,IF(AND(OR(V40="Aprobada con ajuste",V40="Rechazada"),W40<>""),W40,""))
A41: C0040 | B41: Identidad y acceso | C41: auth | D41: geopolitica | E41: 1155 | F41: cod_geopolitica | G41: character varying(20) | H41: No | L41: No | M41: No | P41: Mapeada en auth-service/src/users/geopolitica.entity.ts:15 (Geopolitica.codGeopolitica) | Q41: Propuesta semántica | R41: Código de la división geopolítica. | S41: Media | T41: nombre + tipo + columnas vecinas | U41: ¿cod_geopolitica es el código DANE (Divipola) o un código interno? | V41: Pendiente | AA41: =IF(OR(V41="Aprobada"),R41,IF(AND(OR(V41="Aprobada con ajuste",V41="Rechazada"),W41<>""),W41,""))
A42: C0041 | B42: Identidad y acceso | C42: auth | D42: geopolitica | E42: 1155 | F42: cod_pais | G42: smallint | H42: Sí | L42: No | M42: No | P42: Mapeada en auth-service/src/users/geopolitica.entity.ts:18 (Geopolitica.codPais) | Q42: Propuesta semántica | R42: Código del país de la división geopolítica. | S42: Media | T42: nombre + tipo + columnas vecinas | U42: ¿Qué codificación sigue cod_pais? | V42: Pendiente | AA42: =IF(OR(V42="Aprobada"),R42,IF(AND(OR(V42="Aprobada con ajuste",V42="Rechazada"),W42<>""),W42,""))
A43: C0042 | B43: Identidad y acceso | C43: auth | D43: geopolitica | E43: 1155 | F43: cod_departamento | G43: smallint | H43: Sí | L43: No | M43: No | P43: Mapeada en auth-service/src/users/geopolitica.entity.ts:21 (Geopolitica.codDepartamento) | Q43: Propuesta semántica | R43: Código del departamento de la división geopolítica. | S43: Media | T43: nombre + tipo + columnas vecinas | U43: ¿Es el código DANE del departamento? | V43: Pendiente | AA43: =IF(OR(V43="Aprobada"),R43,IF(AND(OR(V43="Aprobada con ajuste",V43="Rechazada"),W43<>""),W43,""))
A44: C0043 | B44: Identidad y acceso | C44: auth | D44: geopolitica | E44: 1155 | F44: cod_ciudad | G44: smallint | H44: Sí | L44: No | M44: No | P44: Mapeada en auth-service/src/users/geopolitica.entity.ts:24 (Geopolitica.codCiudad) | Q44: Propuesta semántica | R44: Código de la ciudad o municipio de la división geopolítica. | S44: Media | T44: nombre + tipo + columnas vecinas | U44: ¿Es el código DANE del municipio? | V44: Pendiente | AA44: =IF(OR(V44="Aprobada"),R44,IF(AND(OR(V44="Aprobada con ajuste",V44="Rechazada"),W44<>""),W44,""))
A45: C0044 | B45: Identidad y acceso | C45: auth | D45: geopolitica | E45: 1155 | F45: nom_div_geopolitica | G45: character varying(250) | H45: Sí | L45: No | M45: No | P45: Mapeada en auth-service/src/users/geopolitica.entity.ts:27 (Geopolitica.nomDivGeopolitica) | Q45: Propuesta semántica | R45: Nombre de la división geopolítica. | S45: Alta | T45: nombre + tipo + columnas vecinas | V45: Pendiente | AA45: =IF(OR(V45="Aprobada"),R45,IF(AND(OR(V45="Aprobada con ajuste",V45="Rechazada"),W45<>""),W45,""))
A46: C0045 | B46: Identidad y acceso | C46: auth | D46: geopolitica | E46: 1155 | F46: num_habitantes | G46: bigint | H46: Sí | L46: No | M46: No | P46: Mapeada en auth-service/src/users/geopolitica.entity.ts:30 (Geopolitica.numHabitantes) | Q46: Propuesta semántica | R46: Número de habitantes de la división geopolítica. | S46: Alta | T46: nombre + tipo + columnas vecinas | V46: Pendiente | AA46: =IF(OR(V46="Aprobada"),R46,IF(AND(OR(V46="Aprobada con ajuste",V46="Rechazada"),W46<>""),W46,""))
A47: C0046 | B47: Identidad y acceso | C47: auth | D47: geopolitica | E47: 1155 | F47: tip_division | G47: character varying(6) | H47: Sí | L47: No | M47: No | P47: Mapeada en auth-service/src/users/geopolitica.entity.ts:33 (Geopolitica.tipDivision) | Q47: Propuesta semántica | R47: Código del tipo de división geopolítica (país, departamento, municipio). | S47: Media | T47: nombre + tipo + columnas vecinas | U47: ¿Qué valores toma tip_division? | V47: Pendiente | AA47: =IF(OR(V47="Aprobada"),R47,IF(AND(OR(V47="Aprobada con ajuste",V47="Rechazada"),W47<>""),W47,""))
A48: C0047 | B48: Identidad y acceso | C48: auth | D48: geopolitica | E48: 1155 | F48: cod_division | G48: character varying(6) | H48: Sí | L48: No | M48: No | P48: Mapeada en auth-service/src/users/geopolitica.entity.ts:36 (Geopolitica.codDivision) | Q48: Propuesta semántica | R48: Código de la clase de división geopolítica. | S48: Baja | T48: nombre + tipo + columnas vecinas (tip_division) | U48: ¿En qué se diferencia cod_division de tip_division? | V48: Pendiente | AA48: =IF(OR(V48="Aprobada"),R48,IF(AND(OR(V48="Aprobada con ajuste",V48="Rechazada"),W48<>""),W48,""))
A49: C0048 | B49: Identidad y acceso | C49: auth | D49: geopolitica | E49: 1155 | F49: cod_zon_geografica | G49: character varying(6) | H49: Sí | L49: No | M49: No | P49: Mapeada en auth-service/src/users/geopolitica.entity.ts:39 (Geopolitica.codZonGeografica) | Q49: Propuesta semántica | R49: Código de la zona geográfica a la que pertenece la división. | S49: Baja | T49: nombre + tipo + columnas vecinas | U49: ¿Qué valores toma la zona geográfica y de qué catálogo provienen? | V49: Pendiente | AA49: =IF(OR(V49="Aprobada"),R49,IF(AND(OR(V49="Aprobada con ajuste",V49="Rechazada"),W49<>""),W49,""))
A50: C0049 | B50: Identidad y acceso | C50: auth | D50: geopolitica | E50: 1155 | F50: fec_ult_act | G50: date | H50: Sí | L50: No | M50: No | P50: Mapeada en auth-service/src/users/geopolitica.entity.ts:42 (Geopolitica.fecUltAct) | Q50: Propuesta semántica | R50: Fecha de la última actualización del registro. | S50: Alta | T50: nombre + tipo + columnas vecinas | V50: Pendiente | AA50: =IF(OR(V50="Aprobada"),R50,IF(AND(OR(V50="Aprobada con ajuste",V50="Rechazada"),W50<>""),W50,""))
A51: C0050 | B51: Identidad y acceso | C51: auth | D51: geopolitica | E51: 1155 | F51: fec_creacion | G51: date | H51: Sí | L51: No | M51: No | P51: Mapeada en auth-service/src/users/geopolitica.entity.ts:45 (Geopolitica.fecCreacion) | Q51: Propuesta semántica | R51: Fecha de creación del registro. | S51: Alta | T51: nombre + tipo + columnas vecinas | V51: Pendiente | AA51: =IF(OR(V51="Aprobada"),R51,IF(AND(OR(V51="Aprobada con ajuste",V51="Rechazada"),W51<>""),W51,""))
A52: C0051 | B52: Identidad y acceso | C52: auth | D52: geopolitica | E52: 1155 | F52: usu_creacion | G52: character varying(20) | H52: Sí | L52: No | M52: No | P52: Mapeada en auth-service/src/users/geopolitica.entity.ts:48 (Geopolitica.usuCreacion) | Q52: Propuesta semántica | R52: Usuario que creó el registro. | S52: Media | T52: nombre + tipo + columnas vecinas | U52: ¿usu_creacion guarda el nombre de usuario del sistema de origen? | V52: Pendiente | AA52: =IF(OR(V52="Aprobada"),R52,IF(AND(OR(V52="Aprobada con ajuste",V52="Rechazada"),W52<>""),W52,""))
A53: C0052 | B53: Identidad y acceso | C53: auth | D53: geopolitica | E53: 1155 | F53: usu_actualizacion | G53: character varying(20) | H53: Sí | L53: No | M53: No | P53: Mapeada en auth-service/src/users/geopolitica.entity.ts:51 (Geopolitica.usuActualizacion) | Q53: Propuesta semántica | R53: Usuario que hizo la última actualización del registro. | S53: Media | T53: nombre + tipo + columnas vecinas | U53: ¿usu_actualizacion guarda el nombre de usuario del sistema de origen? | V53: Pendiente | AA53: =IF(OR(V53="Aprobada"),R53,IF(AND(OR(V53="Aprobada con ajuste",V53="Rechazada"),W53<>""),W53,""))
A54: C0053 | B54: Identidad y acceso | C54: auth | D54: geopolitica | E54: 1155 | F54: cod_intl_pais | G54: character varying(3) | H54: Sí | L54: No | M54: No | Q54: Propuesta semántica | R54: Código internacional del país (tres caracteres). | S54: Media | T54: nombre + tipo + columnas vecinas | U54: ¿Sigue ISO 3166-1 (alfa-3 o numérico)? | V54: Pendiente | AA54: =IF(OR(V54="Aprobada"),R54,IF(AND(OR(V54="Aprobada con ajuste",V54="Rechazada"),W54<>""),W54,""))
A55: C0054 | B55: Identidad y acceso | C55: auth | D55: geopolitica | E55: 1155 | F55: cod_unso | G55: character varying(3) | H55: Sí | L55: No | M55: No | Q55: Propuesta semántica | R55: Código del país según la clasificación de las Naciones Unidas. | S55: Baja | T55: nombre + tipo + columnas vecinas | U55: ¿Qué significa UNSO y qué codificación sigue? | V55: Pendiente | AA55: =IF(OR(V55="Aprobada"),R55,IF(AND(OR(V55="Aprobada con ajuste",V55="Rechazada"),W55<>""),W55,""))
A56: C0055 | B56: Identidad y acceso | C56: auth | D56: geopolitica | E56: 1155 | F56: cod_dian | G56: character varying(3) | H56: Sí | L56: No | M56: No | Q56: Propuesta semántica | R56: Código del país o división asignado por la DIAN. | S56: Media | T56: nombre + tipo + columnas vecinas | U56: ¿Es el código de país de la DIAN usado en información exógena? | V56: Pendiente | AA56: =IF(OR(V56="Aprobada"),R56,IF(AND(OR(V56="Aprobada con ajuste",V56="Rechazada"),W56<>""),W56,""))
A57: C0056 | B57: Identidad y acceso | C57: auth | D57: geopolitica | E57: 1155 | F57: cod_lat | G57: numeric(11,8) | H57: Sí | L57: No | M57: No | P57: Mapeada en auth-service/src/users/geopolitica.entity.ts:54 (Geopolitica.codLat) | Q57: Propuesta semántica | R57: Latitud geográfica de la división, en grados decimales. | S57: Alta | T57: nombre + tipo + columnas vecinas (cod_lon) | V57: Pendiente | AA57: =IF(OR(V57="Aprobada"),R57,IF(AND(OR(V57="Aprobada con ajuste",V57="Rechazada"),W57<>""),W57,""))
A58: C0057 | B58: Identidad y acceso | C58: auth | D58: geopolitica | E58: 1155 | F58: cod_lon | G58: numeric(11,8) | H58: Sí | L58: No | M58: No | P58: Mapeada en auth-service/src/users/geopolitica.entity.ts:57 (Geopolitica.codLon) | Q58: Propuesta semántica | R58: Longitud geográfica de la división, en grados decimales. | S58: Alta | T58: nombre + tipo + columnas vecinas (cod_lat) | V58: Pendiente | AA58: =IF(OR(V58="Aprobada"),R58,IF(AND(OR(V58="Aprobada con ajuste",V58="Rechazada"),W58<>""),W58,""))
A59: C0058 | B59: Identidad y acceso | C59: auth | D59: geopolitica | E59: 1155 | F59: cod_idioma | G59: character varying(3) | H59: Sí | L59: No | M59: No | Q59: Propuesta semántica | R59: Código del idioma principal de la división geopolítica. | S59: Media | T59: nombre + tipo + columnas vecinas (nom_idioma) | U59: ¿Sigue ISO 639? | V59: Pendiente | AA59: =IF(OR(V59="Aprobada"),R59,IF(AND(OR(V59="Aprobada con ajuste",V59="Rechazada"),W59<>""),W59,""))
A60: C0059 | B60: Identidad y acceso | C60: auth | D60: geopolitica | E60: 1155 | F60: nom_idioma | G60: character varying(250) | H60: Sí | L60: No | M60: No | Q60: Propuesta semántica | R60: Nombre del idioma principal de la división geopolítica. | S60: Media | T60: nombre + tipo + columnas vecinas (cod_idioma) | U60: ¿Se usa este dato en algún módulo? | V60: Pendiente | AA60: =IF(OR(V60="Aprobada"),R60,IF(AND(OR(V60="Aprobada con ajuste",V60="Rechazada"),W60<>""),W60,""))
A61: C0060 | B61: Identidad y acceso | C61: auth | D61: geopolitica | E61: 1155 | F61: cod_idm | G61: character varying(3) | H61: Sí | L61: No | M61: No | Q61: Propuesta semántica | R61: Código de idioma abreviado de la división geopolítica. | S61: Baja | T61: nombre + tipo + columnas vecinas (cod_idioma) | U61: ¿En qué se diferencia cod_idm de cod_idioma? | V61: Pendiente | AA61: =IF(OR(V61="Aprobada"),R61,IF(AND(OR(V61="Aprobada con ajuste",V61="Rechazada"),W61<>""),W61,""))
A62: C0061 | B62: Identidad y acceso | C62: auth | D62: geopolitica | E62: 1155 | F62: nom_div_geopolitica_tot | G62: character varying(200) | H62: Sí | L62: No | M62: No | Q62: Propuesta semántica | R62: Nombre completo de la división geopolítica con su jerarquía (por ejemplo, municipio, departamento y país). | S62: Media | T62: nombre + tipo + columnas vecinas (nom_div_geopolitica) | U62: ¿El nombre total concatena la jerarquía de la división? | V62: Pendiente | AA62: =IF(OR(V62="Aprobada"),R62,IF(AND(OR(V62="Aprobada con ajuste",V62="Rechazada"),W62<>""),W62,""))
A63: C0062 | B63: Identidad y acceso | C63: auth | D63: geopolitica | E63: 1155 | F63: cod_are_tel | G63: character varying(6) | H63: Sí | L63: No | M63: No | Q63: Propuesta semántica | R63: Código de área telefónica (indicativo) de la división geopolítica. | S63: Media | T63: nombre + tipo + columnas vecinas | U63: ¿Es el indicativo telefónico nacional o internacional? | V63: Pendiente | AA63: =IF(OR(V63="Aprobada"),R63,IF(AND(OR(V63="Aprobada con ajuste",V63="Rechazada"),W63<>""),W63,""))
A64: C0063 | B64: Identidad y acceso | C64: auth | D64: geopolitica | E64: 1155 | F64: cod_pais_defecto | G64: character varying(3) | H64: Sí | L64: No | M64: No | Q64: Propuesta semántica | R64: Código del país por defecto asociado a la división geopolítica. | S64: Baja | T64: nombre + tipo + columnas vecinas | U64: ¿Para qué se usa cod_pais_defecto? | V64: Pendiente | AA64: =IF(OR(V64="Aprobada"),R64,IF(AND(OR(V64="Aprobada con ajuste",V64="Rechazada"),W64<>""),W64,""))
A65: C0064 | B65: Identidad y acceso | C65: auth | D65: geopolitica | E65: 1155 | F65: ind_oculto | G65: smallint | H65: No | L65: No | M65: No | P65: Mapeada en auth-service/src/users/geopolitica.entity.ts:70 (Geopolitica.indOculto) | Q65: Propuesta semántica | R65: Indicador de si la división geopolítica se oculta en las listas de selección. | S65: Media | T65: nombre + tipo + columnas vecinas (smallint) | U65: ¿Qué valores toma ind_oculto (0 y 1)? | V65: Pendiente | AA65: =IF(OR(V65="Aprobada"),R65,IF(AND(OR(V65="Aprobada con ajuste",V65="Rechazada"),W65<>""),W65,""))
A66: C0065 | B66: Identidad y acceso | C66: auth | D66: migrations_db_log | E66: 1221 | F66: executed_at | G66: timestamp without time zone | H66: Sí | L66: Sí | M66: No | Q66: Propuesta semántica | R66: Fecha y hora en que se ejecutó el archivo de migración. Por defecto, la fecha y hora del registro. | S66: Alta | T66: nombre + tipo + columnas vecinas (filename) + defecto now() | V66: Pendiente | AA66: =IF(OR(V66="Aprobada"),R66,IF(AND(OR(V66="Aprobada con ajuste",V66="Rechazada"),W66<>""),W66,""))
A67: C0066 | B67: Identidad y acceso | C67: auth | D67: module | E67: 23 | F67: code | G67: character varying(50) | H67: No | I67: Única | L67: No | M67: Sí | N67: Vista hiring.roles_del_modulo | O67: module_code_key | P67: Mapeada en auth-service/src/users/module.entity.ts:9 (Module.code) | Validación: IsString, Matches(/^\d{6}$/, { message: 'El código debe tener 6 dígitos' }) | Q67: Regla estructural | R67: Código del registro de module. Único en la tabla. | S67: Media | T67: Convención de nombre de la columna. | V67: Pendiente | AA67: =IF(OR(V67="Aprobada"),R67,IF(AND(OR(V67="Aprobada con ajuste",V67="Rechazada"),W67<>""),W67,""))
A68: C0067 | B68: Identidad y acceso | C68: auth | D68: module | E68: 23 | F68: name | G68: character varying(100) | H68: No | L68: No | M68: Sí | N68: Vista hiring.roles_del_modulo | P68: Mapeada en auth-service/src/users/module.entity.ts:12 (Module.name) | Validación: IsOptional, IsString | Q68: Regla estructural | R68: Nombre del registro de module. | S68: Media | T68: Convención de nombre de la columna. | V68: Pendiente | AA68: =IF(OR(V68="Aprobada"),R68,IF(AND(OR(V68="Aprobada con ajuste",V68="Rechazada"),W68<>""),W68,""))
A69: C0068 | B69: Identidad y acceso | C69: auth | D69: module | E69: 23 | F69: description | G69: text | H69: Sí | L69: No | M69: No | P69: Mapeada en auth-service/src/users/module.entity.ts:15 (Module.description) | Validación: IsOptional, IsString | Q69: Regla estructural | R69: Descripción del registro de module. | S69: Media | T69: Convención de nombre de la columna. | V69: Pendiente | AA69: =IF(OR(V69="Aprobada"),R69,IF(AND(OR(V69="Aprobada con ajuste",V69="Rechazada"),W69<>""),W69,""))
A70: C0069 | B70: Identidad y acceso | C70: auth | D70: module | E70: 23 | F70: icon | G70: character varying(50) | H70: Sí | L70: No | M70: No | P70: Mapeada en auth-service/src/users/module.entity.ts:18 (Module.icon) | Validación: IsOptional, IsString | Q70: Propuesta semántica | R70: Nombre del ícono con que se muestra el módulo en la interfaz. Por defecto, Shield. | S70: Alta | T70: nombre + tipo + columnas vecinas + defecto | V70: Pendiente | AA70: =IF(OR(V70="Aprobada"),R70,IF(AND(OR(V70="Aprobada con ajuste",V70="Rechazada"),W70<>""),W70,""))
A71: C0070 | B71: Identidad y acceso | C71: auth | D71: module | E71: 23 | F71: color | G71: character varying(20) | H71: Sí | L71: No | M71: No | P71: Mapeada en auth-service/src/users/module.entity.ts:21 (Module.color) | Validación: IsOptional, IsString | Q71: Propuesta semántica | R71: Color del módulo en la interfaz, en formato hexadecimal. Por defecto, #003DA5. | S71: Alta | T71: nombre + tipo + columnas vecinas + defecto | V71: Pendiente | AA71: =IF(OR(V71="Aprobada"),R71,IF(AND(OR(V71="Aprobada con ajuste",V71="Rechazada"),W71<>""),W71,""))
A72: C0071 | B72: Identidad y acceso | C72: auth | D72: module | E72: 23 | F72: display_order | G72: integer | H72: Sí | L72: No | M72: No | P72: Mapeada en auth-service/src/users/module.entity.ts:24 (Module.display_order) | Validación: IsNumber, IsOptional | Q72: Propuesta semántica | R72: Posición del módulo en las listas de presentación. Por defecto, 0. | S72: Alta | T72: nombre + tipo + columnas vecinas + defecto | V72: Pendiente | AA72: =IF(OR(V72="Aprobada"),R72,IF(AND(OR(V72="Aprobada con ajuste",V72="Rechazada"),W72<>""),W72,""))
A73: C0072 | B73: Identidad y acceso | C73: auth | D73: module | E73: 23 | F73: category | G73: character varying(30) | H73: No | L73: No | M73: No | P73: db/init/old/001_schema_auth.sql:475: backoffice | portal | Validación: IsIn(['backoffice', 'portal']), IsOptional | Q73: Código fuente | R73: Categoría del módulo según la aplicación donde se presenta. Valores previstos: backoffice, portal; por defecto backoffice. | S73: Alta | T73: código: db/init/old/001_schema_auth.sql:475 | V73: Pendiente | AA73: =IF(OR(V73="Aprobada"),R73,IF(AND(OR(V73="Aprobada con ajuste",V73="Rechazada"),W73<>""),W73,""))
A74: C0073 | B74: Identidad y acceso | C74: auth | D74: module | E74: 23 | F74: is_active | G74: boolean | H74: Sí | L74: No | M74: Sí | N74: Vista hiring.roles_del_modulo | P74: Mapeada en auth-service/src/users/module.entity.ts:30 (Module.is_active) | Validación: IsBoolean, IsOptional | Q74: Regla estructural | R74: Indica si el registro está activo. | S74: Media | T74: Convención de nombre de la columna. | V74: Pendiente | AA74: =IF(OR(V74="Aprobada"),R74,IF(AND(OR(V74="Aprobada con ajuste",V74="Rechazada"),W74<>""),W74,""))
A75: C0074 | B75: Identidad y acceso | C75: auth | D75: permission | E75: 704 | F75: code | G75: character varying(100) | H75: No | I75: Única | L75: No | M75: Sí | N75: Vista hiring.roles_del_modulo | O75: permission_code_key | P75: Mapeada en auth-service/src/users/permission.entity.ts:10 (Permission.code) | Validación: IsString, Matches(/^\d{6}$/, { message: 'El código debe tener 6 dígitos' }) | Q75: Regla estructural | R75: Código del registro de permission. Único en la tabla. | S75: Media | T75: Convención de nombre de la columna. | V75: Pendiente | AA75: =IF(OR(V75="Aprobada"),R75,IF(AND(OR(V75="Aprobada con ajuste",V75="Rechazada"),W75<>""),W75,""))
A76: C0075 | B76: Identidad y acceso | C76: auth | D76: permission | E76: 704 | F76: name | G76: character varying(150) | H76: No | L76: No | M76: Sí | N76: Vista hiring.roles_del_modulo | P76: Mapeada en auth-service/src/users/permission.entity.ts:13 (Permission.name) | Validación: IsOptional, IsString | Q76: Regla estructural | R76: Nombre del registro de permission. | S76: Media | T76: Convención de nombre de la columna. | V76: Pendiente | AA76: =IF(OR(V76="Aprobada"),R76,IF(AND(OR(V76="Aprobada con ajuste",V76="Rechazada"),W76<>""),W76,""))
A77: C0076 | B77: Identidad y acceso | C77: auth | D77: permission | E77: 704 | F77: description | G77: text | H77: Sí | L77: No | M77: No | P77: Mapeada en auth-service/src/users/permission.entity.ts:16 (Permission.description) | Validación: IsOptional, IsString | Q77: Regla estructural | R77: Descripción del registro de permission. | S77: Media | T77: Convención de nombre de la columna. | V77: Pendiente | AA77: =IF(OR(V77="Aprobada"),R77,IF(AND(OR(V77="Aprobada con ajuste",V77="Rechazada"),W77<>""),W77,""))
A78: C0077 | B78: Identidad y acceso | C78: auth | D78: permission | E78: 704 | F78: is_active | G78: boolean | H78: Sí | L78: No | M78: Sí | N78: Vista hiring.roles_del_modulo | P78: Mapeada en auth-service/src/users/permission.entity.ts:22 (Permission.is_active) | Validación: IsBoolean, IsOptional | Q78: Regla estructural | R78: Indica si el registro está activo. | S78: Media | T78: Convención de nombre de la columna. | V78: Pendiente | AA78: =IF(OR(V78="Aprobada"),R78,IF(AND(OR(V78="Aprobada con ajuste",V78="Rechazada"),W78<>""),W78,""))
A79: C0078 | B79: Identidad y acceso | C79: auth | D79: personas | E79: 409 | F79: num_identificacion | G79: character varying(30) | H79: No | L79: No | M79: Sí | N79: Trigger trg_auth_personas_rund_document_immutable; Vista control_interno.v_auditor_disponibilidad | P79: Mapeada en auth-service/src/users/person.entity.ts:17 (Person.identification_number) | Validación: IsString | Q79: Regla estructural | R79: Número de identificación. | S79: Media | T79: Convención de nombre de la columna. | V79: Pendiente | AA79: =IF(OR(V79="Aprobada"),R79,IF(AND(OR(V79="Aprobada con ajuste",V79="Rechazada"),W79<>""),W79,""))
A80: C0079 | B80: Identidad y acceso | C80: auth | D80: personas | E80: 409 | F80: tip_identificacion | G80: character varying(6) | H80: No | L80: No | M80: Sí | N80: Vista control_interno.v_auditor_disponibilidad | P80: Mapeada en auth-service/src/users/person.entity.ts:20 (Person.identification_type) | Validación: IsString | Q80: Propuesta semántica | R80: Código del tipo de documento de identidad de la persona. | S80: Media | T80: nombre + tipo + columnas vecinas (num_identificacion) | U80: ¿Qué valores toma tip_identificacion (CC, CE, TI, PA…)? | V80: Pendiente | AA80: =IF(OR(V80="Aprobada"),R80,IF(AND(OR(V80="Aprobada con ajuste",V80="Rechazada"),W80<>""),W80,""))
A81: C0080 | B81: Identidad y acceso | C81: auth | D81: personas | E81: 409 | F81: nom_largo | G81: character varying(1000) | H81: No | L81: No | M81: Sí | N81: Vista control_interno.v_auditor_disponibilidad; Vista control_interno.v_auditorias_kanban_completo | P81: Mapeada en auth-service/src/users/person.entity.ts:23 (Person.full_name) | Q81: Propuesta semántica | R81: Nombre completo de la persona (nombres y apellidos). | S81: Media | T81: nombre + tipo + columnas vecinas (nom_tercero, pri_apellido, seg_apellido) | U81: ¿nom_largo se forma concatenando nombres y apellidos? | V81: Pendiente | AA81: =IF(OR(V81="Aprobada"),R81,IF(AND(OR(V81="Aprobada con ajuste",V81="Rechazada"),W81<>""),W81,""))
A82: C0081 | B82: Identidad y acceso | C82: auth | D82: personas | E82: 409 | F82: nom_tercero | G82: character varying(250) | H82: No | L82: No | M82: No | P82: Mapeada en auth-service/src/users/person.entity.ts:26 (Person.first_name) | Validación: IsString | Q82: Propuesta semántica | R82: Nombres de la persona. | S82: Media | T82: nombre + tipo + columnas vecinas (pri_apellido, seg_apellido) | U82: ¿nom_tercero guarda solo los nombres o el nombre completo? | V82: Pendiente | AA82: =IF(OR(V82="Aprobada"),R82,IF(AND(OR(V82="Aprobada con ajuste",V82="Rechazada"),W82<>""),W82,""))
A83: C0082 | B83: Identidad y acceso | C83: auth | D83: personas | E83: 409 | F83: pri_apellido | G83: character varying(250) | H83: Sí | L83: No | M83: No | P83: Mapeada en auth-service/src/users/person.entity.ts:29 (Person.last_name) | Validación: IsString | Q83: Propuesta semántica | R83: Primer apellido de la persona. | S83: Alta | T83: nombre + tipo + columnas vecinas | V83: Pendiente | AA83: =IF(OR(V83="Aprobada"),R83,IF(AND(OR(V83="Aprobada con ajuste",V83="Rechazada"),W83<>""),W83,""))
A84: C0083 | B84: Identidad y acceso | C84: auth | D84: personas | E84: 409 | F84: seg_apellido | G84: character varying(250) | H84: Sí | L84: No | M84: No | Q84: Propuesta semántica | R84: Segundo apellido de la persona. | S84: Alta | T84: nombre + tipo + columnas vecinas | V84: Pendiente | AA84: =IF(OR(V84="Aprobada"),R84,IF(AND(OR(V84="Aprobada con ajuste",V84="Rechazada"),W84<>""),W84,""))
A85: C0084 | B85: Identidad y acceso | C85: auth | D85: personas | E85: 409 | F85: gen_tercero | G85: character varying(6) | H85: No | L85: No | M85: No | O85: idx_personas_gen_tercero | P85: Mapeada en auth-service/src/users/person.entity.ts:32 (Person.gender) | Validación: IsOptional, IsString | Q85: Propuesta semántica | R85: Código del género de la persona. | S85: Media | T85: nombre + tipo + columnas vecinas | U85: ¿Qué valores toma gen_tercero? | V85: Pendiente | AA85: =IF(OR(V85="Aprobada"),R85,IF(AND(OR(V85="Aprobada con ajuste",V85="Rechazada"),W85<>""),W85,""))
A86: C0085 | B86: Identidad y acceso | C86: auth | D86: personas | E86: 409 | F86: fec_nacimiento | G86: date | H86: Sí | L86: No | M86: No | P86: Mapeada en auth-service/src/users/person.entity.ts:85 (Person.fec_nacimiento) | Q86: Propuesta semántica | R86: Fecha de nacimiento de la persona. | S86: Alta | T86: nombre + tipo + columnas vecinas | V86: Pendiente | AA86: =IF(OR(V86="Aprobada"),R86,IF(AND(OR(V86="Aprobada con ajuste",V86="Rechazada"),W86<>""),W86,""))
A87: C0086 | B87: Identidad y acceso | C87: auth | D87: personas | E87: 409 | F87: dir_residencia | G87: character varying(250) | H87: Sí | L87: No | M87: No | P87: Mapeada en auth-service/src/users/person.entity.ts:88 (Person.dir_residencia) | Q87: Propuesta semántica | R87: Dirección de residencia de la persona. | S87: Alta | T87: nombre + tipo + columnas vecinas | V87: Pendiente | AA87: =IF(OR(V87="Aprobada"),R87,IF(AND(OR(V87="Aprobada con ajuste",V87="Rechazada"),W87<>""),W87,""))
A88: C0087 | B88: Identidad y acceso | C88: auth | D88: personas | E88: 409 | F88: dir_email | G88: character varying(100) | H88: Sí | L88: No | M88: Sí | N88: Vista control_interno.v_auditor_disponibilidad; Vista control_interno.v_auditorias_kanban_completo | P88: Mapeada en auth-service/src/users/person.entity.ts:35 (Person.email) | Validación: IsEmail, IsOptional, IsString | Q88: Propuesta semántica | R88: Correo electrónico de la persona. | S88: Media | T88: nombre + tipo + columnas vecinas + validación IsEmail | U88: ¿Es el correo institucional o el personal? | V88: Pendiente | AA88: =IF(OR(V88="Aprobada"),R88,IF(AND(OR(V88="Aprobada con ajuste",V88="Rechazada"),W88<>""),W88,""))
A89: C0088 | B89: Identidad y acceso | C89: auth | D89: personas | E89: 409 | F89: tel_celular | G89: character varying(255) | H89: Sí | L89: No | M89: No | P89: Mapeada en auth-service/src/users/person.entity.ts:38 (Person.phone) | Validación: IsOptional, IsString | Q89: Propuesta semántica | R89: Número de teléfono celular de la persona. | S89: Alta | T89: nombre + tipo + columnas vecinas | V89: Pendiente | AA89: =IF(OR(V89="Aprobada"),R89,IF(AND(OR(V89="Aprobada con ajuste",V89="Rechazada"),W89<>""),W89,""))
A90: C0089 | B90: Identidad y acceso | C90: auth | D90: personas | E90: 409 | F90: fec_creacion | G90: timestamp with time zone | H90: Sí | L90: No | M90: No | P90: Mapeada en auth-service/src/users/person.entity.ts:42 (Person.created_at) | Q90: Propuesta semántica | R90: Fecha y hora de creación del registro. Por defecto, la fecha y hora del registro. | S90: Alta | T90: nombre + tipo + columnas vecinas + defecto | V90: Pendiente | AA90: =IF(OR(V90="Aprobada"),R90,IF(AND(OR(V90="Aprobada con ajuste",V90="Rechazada"),W90<>""),W90,""))
A91: C0090 | B91: Identidad y acceso | C91: auth | D91: personas | E91: 409 | F91: fec_modificacion | G91: timestamp with time zone | H91: Sí | L91: No | M91: No | P91: Mapeada en auth-service/src/users/person.entity.ts:45 (Person.updated_at) | Q91: Propuesta semántica | R91: Fecha y hora de la última modificación del registro. | S91: Alta | T91: nombre + tipo + columnas vecinas | V91: Pendiente | AA91: =IF(OR(V91="Aprobada"),R91,IF(AND(OR(V91="Aprobada con ajuste",V91="Rechazada"),W91<>""),W91,""))
A92: C0091 | B92: Identidad y acceso | C92: auth | D92: personas | E92: 409 | F92: usu_creacion | G92: character varying(20) | H92: Sí | L92: No | M92: No | Q92: Propuesta semántica | R92: Usuario que creó el registro. | S92: Media | T92: nombre + tipo + columnas vecinas | U92: ¿usu_creacion guarda el nombre de usuario o el identificador? | V92: Pendiente | AA92: =IF(OR(V92="Aprobada"),R92,IF(AND(OR(V92="Aprobada con ajuste",V92="Rechazada"),W92<>""),W92,""))
A93: C0092 | B93: Identidad y acceso | C93: auth | D93: personas | E93: 409 | F93: usu_modificacion | G93: character varying(20) | H93: Sí | L93: No | M93: No | Q93: Propuesta semántica | R93: Usuario que hizo la última modificación del registro. | S93: Media | T93: nombre + tipo + columnas vecinas | U93: ¿usu_modificacion guarda el nombre de usuario o el identificador? | V93: Pendiente | AA93: =IF(OR(V93="Aprobada"),R93,IF(AND(OR(V93="Aprobada con ajuste",V93="Rechazada"),W93<>""),W93,""))
A94: C0093 | B94: Identidad y acceso | C94: auth | D94: personas | E94: 409 | F94: id_person | G94: uuid | H94: No | I94: Única | L94: No | M94: Sí | N94: Función control_interno.fn_registrar_cambio_estado_auditoria; Función control_interno.fn_registrar_cambio_estado_plan_anual; Vista control_interno.v_auditor_disponibilidad; Vista control_interno.v_auditorias_kanban_completo — control_interno.fn_registrar_cambio_estado_auditoria: SELECT id_person INTO v_usuario_id | control_interno.fn_registrar_cambio_estado_plan_anual: SELECT id_person INTO v_usuario_id | O94: personas_id_person_key | P94: Mapeada en auth-service/src/users/person.entity.ts:11 (Person.id) | Q94: Propuesta semántica | R94: Identificador único (UUID) de la persona, usado por las demás tablas para enlazarla; se genera automáticamente. | S94: Alta | T94: nombre + tipo + columnas vecinas + restricción única + uso en funciones de control_interno | V94: Pendiente | AA94: =IF(OR(V94="Aprobada"),R94,IF(AND(OR(V94="Aprobada con ajuste",V94="Rechazada"),W94<>""),W94,""))
A95: C0094 | B95: Identidad y acceso | C95: auth | D95: personas | E95: 409 | F95: city | G95: character varying(255) | H95: Sí | L95: No | M95: No | P95: Mapeada en auth-service/src/users/person.entity.ts:91 (Person.city) | Validación: IsOptional, IsString | Q95: Propuesta semántica | R95: Ciudad de la persona. | S95: Media | T95: nombre + tipo + columnas vecinas | U95: ¿Es la ciudad de residencia y por qué no se usa id de auth.geopolitica? | V95: Pendiente | AA95: =IF(OR(V95="Aprobada"),R95,IF(AND(OR(V95="Aprobada con ajuste",V95="Rechazada"),W95<>""),W95,""))
A96: C0095 | B96: Identidad y acceso | C96: auth | D96: programas_academicos | E96: 12 | F96: codigo | G96: text | H96: No | I96: Única | L96: No | M96: No | O96: programas_academicos_codigo_key | Q96: Regla estructural | R96: Código del registro de programas_academicos. Único en la tabla. | S96: Media | T96: Convención de nombre de la columna. | V96: Pendiente | AA96: =IF(OR(V96="Aprobada"),R96,IF(AND(OR(V96="Aprobada con ajuste",V96="Rechazada"),W96<>""),W96,""))
A97: C0096 | B97: Identidad y acceso | C97: auth | D97: programas_academicos | E97: 12 | F97: nombre | G97: text | H97: No | L97: No | M97: No | Q97: Regla estructural | R97: Nombre del registro de programas_academicos. | S97: Media | T97: Convención de nombre de la columna. | V97: Pendiente | AA97: =IF(OR(V97="Aprobada"),R97,IF(AND(OR(V97="Aprobada con ajuste",V97="Rechazada"),W97<>""),W97,""))
A98: C0097 | B98: Identidad y acceso | C98: auth | D98: programas_academicos | E98: 12 | F98: nivel_formacion | G98: text | H98: No | L98: No | M98: No | P98: db/migrations/old/006_create_programas_academicos.sql:12: Pregrado, Especialización, Maestría, Doctorado, etc. | Q98: Código fuente | R98: Nivel de formación del programa (por ejemplo, Pregrado, Especialización, Maestría, Doctorado). | S98: Alta | T98: código: db/migrations/old/006_create_programas_academicos.sql:12 | V98: Pendiente | AA98: =IF(OR(V98="Aprobada"),R98,IF(AND(OR(V98="Aprobada con ajuste",V98="Rechazada"),W98<>""),W98,""))
A99: C0098 | B99: Identidad y acceso | C99: auth | D99: programas_academicos | E99: 12 | F99: modalidad | G99: text | H99: No | L99: No | M99: No | P99: db/migrations/old/006_create_programas_academicos.sql:13: Presencial, Virtual, Distancia, Dual | Q99: Código fuente | R99: Modalidad del programa (por ejemplo, Presencial, Virtual, Distancia, Dual). | S99: Alta | T99: código: db/migrations/old/006_create_programas_academicos.sql:13 | V99: Pendiente | AA99: =IF(OR(V99="Aprobada"),R99,IF(AND(OR(V99="Aprobada con ajuste",V99="Rechazada"),W99<>""),W99,""))
A100: C0099 | B100: Identidad y acceso | C100: auth | D100: programas_academicos | E100: 12 | F100: jornada | G100: text | H100: No | L100: No | M100: No | P100: db/migrations/old/006_create_programas_academicos.sql:14: Diurna, Nocturna, Mixta, Flexible | Q100: Código fuente | R100: Jornada del programa (por ejemplo, Diurna, Nocturna, Mixta, Flexible). | S100: Alta | T100: código: db/migrations/old/006_create_programas_academicos.sql:14 | V100: Pendiente | AA100: =IF(OR(V100="Aprobada"),R100,IF(AND(OR(V100="Aprobada con ajuste",V100="Rechazada"),W100<>""),W100,""))
...

Sheet Uso en lógica
A1: Esquema | B1: Tabla | C1: Columna | D1: Objeto | E1: Tipo de objeto | F1: Líneas donde aparece la columna
A2: auth | B2: module | C2: code | D2: hiring.roles_del_modulo | E2: Vista
A3: auth | B3: module | C3: name | D3: hiring.roles_del_modulo | E3: Vista
A4: auth | B4: module | C4: is_active | D4: hiring.roles_del_modulo | E4: Vista
A5: auth | B5: permission | C5: code | D5: hiring.roles_del_modulo | E5: Vista
A6: auth | B6: permission | C6: name | D6: hiring.roles_del_modulo | E6: Vista
A7: auth | B7: permission | C7: is_active | D7: hiring.roles_del_modulo | E7: Vista
A8: auth | B8: personas | C8: num_identificacion | D8: trg_auth_personas_rund_document_immutable | E8: Trigger (UPDATE OF)
A9: auth | B9: personas | C9: num_identificacion | D9: control_interno.v_auditor_disponibilidad | E9: Vista
A10: auth | B10: personas | C10: tip_identificacion | D10: control_interno.v_auditor_disponibilidad | E10: Vista
A11: auth | B11: personas | C11: nom_largo | D11: control_interno.v_auditor_disponibilidad | E11: Vista
A12: auth | B12: personas | C12: nom_largo | D12: control_interno.v_auditorias_kanban_completo | E12: Vista
A13: auth | B13: personas | C13: dir_email | D13: control_interno.v_auditor_disponibilidad | E13: Vista
A14: auth | B14: personas | C14: dir_email | D14: control_interno.v_auditorias_kanban_completo | E14: Vista
A15: auth | B15: personas | C15: id_person | D15: control_interno.fn_registrar_cambio_estado_auditoria | E15: Función | F15: SELECT id_person INTO v_usuario_id
A16: auth | B16: personas | C16: id_person | D16: control_interno.fn_registrar_cambio_estado_plan_anual | E16: Función | F16: SELECT id_person INTO v_usuario_id
A17: auth | B17: personas | C17: id_person | D17: control_interno.v_auditor_disponibilidad | E17: Vista
A18: auth | B18: personas | C18: id_person | D18: control_interno.v_auditorias_kanban_completo | E18: Vista
A19: auth | B19: role | C19: code | D19: hiring.roles_del_modulo | E19: Vista
A20: auth | B20: role | C20: name | D20: hiring.roles_del_modulo | E20: Vista
A21: auth | B21: role | C21: type | D21: hiring.roles_del_modulo | E21: Vista
A22: auth | B22: role | C22: is_active | D22: hiring.roles_del_modulo | E22: Vista
A23: auth | B23: role_permissions | C23: is_active | D23: hiring.roles_del_modulo | E23: Vista
A24: academic_registration | B24: graduates | C24: full_name | D24: trg_validate_graduate_management_update | E24: Trigger (UPDATE OF)
A25: academic_registration | B25: graduates | C25: id_number | D25: trg_validate_graduate_management_update | E25: Trigger (UPDATE OF)
A26: academic_registration | B26: graduates | C26: email | D26: trg_validate_graduate_management_update | E26: Trigger (UPDATE OF)
A27: academic_registration | B27: graduates | C27: first_name | D27: trg_validate_graduate_management_update | E27: Trigger (UPDATE OF)
A28: academic_registration | B28: graduates | C28: last_name | D28: trg_validate_graduate_management_update | E28: Trigger (UPDATE OF)
A29: academic_work_plan | B29: Docente | C29: estado | D29: academic_work_plan.prevent_rund_document_change | E29: Función | F29: AND s.estado = 'PENDIENTE' AND j.estado = 'COMPLETADO' AND doc.estado = 'ACTIVO'
A30: academic_work_plan | B30: Documento | C30: nombre | D30: academic_registration.validate_graduate_management_update | E30: Función | F30: 'El nombre completo debe tener entre 5 y 150 caracteres y solo puede contener letras, espacios, apostrofes y guiones.' 'El nombre solo puede contener letras, espacios, apostrofes y guiones.'
A31: academic_work_plan | B31: Documento | C31: tipo | D31: control_interno.actualizar_contadores_documentos_informes | E31: Función | F31: -- Determinar el ID de la auditoría y el tipo de documento -- Determinar si es un informe basado en el tipo de documento
A32: academic_work_plan | B32: Documento | C32: estado | D32: academic_work_plan.prevent_rund_document_change | E32: Función | F32: AND s.estado = 'PENDIENTE' AND j.estado = 'COMPLETADO' AND doc.estado = 'ACTIVO'
A33: academic_work_plan | B33: periodo_academico | C33: codigo | D33: academic-schedule.reapuntar_grupos_por_equivalencia | E33: Función | F33: JOIN "academic-schedule".equivalencia_periodo e ON e.codigo_programacion = pp.codigo JOIN academic_work_plan.periodo_academico pa ON pa.codigo = e.codigo_periodo_academico
A34: academic_work_plan | B34: programa | C34: nombre | D34: control_interno.fn_configurar_actividad_auditorias_plan | E34: Función | F34: LOWER(a.nombre) LIKE '%auditoría%' OR LOWER(a.nombre) LIKE '%auditoria%' OR LOWER(a.nombre) LIKE '%programa de auditor%'
A35: academic_work_plan | B35: Rol | C35: nombre | D35: control_interno.fn_configurar_actividad_auditorias_plan | E35: Función | F35: LOWER(a.nombre) LIKE '%auditoría%' OR LOWER(a.nombre) LIKE '%auditoria%' OR LOWER(a.nombre) LIKE '%programa de auditor%'
A36: academic_work_plan | B36: RundDocumentoPerfil | C36: docente_id | D36: academic_work_plan.prevent_rund_document_change | E36: Función | F36: JOIN academic_work_plan."Docente" d ON d.id::text = j.docente_id::text
A37: academic_work_plan | B37: RundDocumentoPerfil | C37: estado | D37: academic_work_plan.prevent_rund_document_change | E37: Función | F37: AND s.estado = 'PENDIENTE' AND j.estado = 'COMPLETADO' AND doc.estado = 'ACTIVO'
A38: academic_work_plan | B38: RundExtraccionSugerencia | C38: campo | D38: academic_work_plan.prevent_rund_document_change | E38: Función | F38: AND s.campo = 'documentNumber'
A39: academic_work_plan | B39: RundExtraccionSugerencia | C39: valor | D39: academic_work_plan.prevent_rund_document_change | E39: Función | F39: AND regexp_replace(UPPER(BTRIM(s.valor)), '[^A-Z0-9]', '', 'g') =
A40: academic_work_plan | B40: RundExtraccionSugerencia | C40: estado | D40: academic_work_plan.prevent_rund_document_change | E40: Función | F40: AND s.estado = 'PENDIENTE' AND j.estado = 'COMPLETADO' AND doc.estado = 'ACTIVO'
... A42: academic_work_plan | B42: RundExtraccionTrabajo | C42: estado | D42: academic_work_plan.prevent_rund_document_change | E42: Función | F42: AND s.estado = 'PENDIENTE' AND j.estado = 'COMPLETADO' AND doc.estado = 'ACTIVO'
A43: academic_work_plan | B43: Territorial | C43: nombre | D43: control_interno.v_auditorias_kanban_completo | E43: Vista
A44: academic_work_plan | B44: Territorial | C44: codigo | D44: control_interno.v_auditorias_kanban_completo | E44: Vista
A45: legal_management | B45: hallazgos | C45: titulo | D45: control_interno.v_auditorias_kanban_completo | E45: Vista
A46: legal_management | B46: hallazgos | C46: descripcion | D46: control_interno.v_auditorias_kanban_completo | E46: Vista
A47: legal_management | B47: hallazgos | C47: estado | D47: control_interno.v_auditorias_kanban_completo | E47: Vista
A48: legal_management | B48: hallazgos | C48: estado | D48: control_interno.v_auditorias_por_estado | E48: Vista
A49: control_interno | B49: accion_correctiva | C49: descripcion | D49: control_interno.trigger_evento_actualizacion_accion | E49: Función | F49: v_descripcion := 'Acción completada: ' || SUBSTRING(NEW.descripcion, 1, 100) || CASE WHEN LENGTH(NEW.descripcion) > 100 THEN '...' ELSE '' END; v_descripcion := 'Acción actualizada: ' || SUBSTRING(NEW.descripcion, 1, 100) ||
A50: control_interno | B50: accion_correctiva | C50: descripcion | D50: control_interno.trigger_evento_creacion_accion | E50: Función | F50: 'Nueva acción creada: ' || SUBSTRING(NEW.descripcion, 1, 100) || CASE WHEN LENGTH(NEW.descripcion) > 100 THEN '...' ELSE '' END,
A51: control_interno | B51: accion_correctiva | C51: tipo | D51: control_interno.trigger_evento_actualizacion_accion | E51: Función | F51: -- Determinar el tipo de evento según lo que cambió
A52: control_interno | B52: accion_correctiva | C52: responsable | D52: control_interno.trigger_evento_actualizacion_accion | E52: Función | F52: NEW.responsable, -- usar el campo responsable que es varchar
A53: control_interno | B53: accion_correctiva | C53: responsable | D53: control_interno.trigger_evento_creacion_accion | E53: Función | F53: NEW.responsable, -- usar el campo responsable que es varchar
A54: control_interno | B54: accion_correctiva | C54: estado | D54: control_interno.trigger_evento_actualizacion_accion | E54: Función | F54: ELSIF OLD.estado IS DISTINCT FROM NEW.estado THEN v_tipo := 'ESTADO'::control_interno.tipo_evento_timeline; v_descripcion := 'Estado de acción actualizado: ' || OLD.estado || ' → ' || NEW.estado;
A55: control_interno | B55: accion_correctiva | C55: estado | D55: control_interno.trigger_evento_creacion_accion | E55: Función | F55: 'estado', NEW.estado,
A56: control_interno | B56: accion_correctiva | C56: porcentaje_avance | D56: control_interno.trigger_evento_actualizacion_accion | E56: Función | F56: IF OLD.porcentaje_avance IS DISTINCT FROM NEW.porcentaje_avance THEN v_descripcion := 'Progreso actualizado: ' || OLD.porcentaje_avance || '% → ' || NEW.porcentaje_avance || '%'; 'progreso_anterior', OLD.porcentaje_avance,
A57: control_interno | B57: accion_correctiva | C57: porcentaje_avance | D57: control_interno.trigger_evento_creacion_accion | E57: Función | F57: 'progreso', NEW.porcentaje_avance
A58: control_interno | B58: actividad_plan_anual_5 | C58: plan_id | D58: control_interno.fn_actualizar_cumplimiento_auditorias_vigencia | E58: Función | F58: INNER JOIN control_interno.plan_anual_5_roles p ON r.plan_id = p.id
A59: control_interno | B59: actividad_plan_anual_5 | C59: plan_id | D59: control_interno.fn_configurar_actividad_auditorias_plan | E59: Función | F59: WHERE r.plan_id = p_plan_id WHERE r.plan_id = p_plan_id AND r.plan_id = p_plan_id
A60: control_interno | B60: actividad_plan_anual_5 | C60: plan_id | D60: control_interno.v_estado_vinculacion_auditorias | E60: Vista
A61: control_interno | B61: actividad_plan_anual_5 | C61: nombre | D61: control_interno.fn_configurar_actividad_auditorias_plan | E61: Función | F61: LOWER(a.nombre) LIKE '%auditoría%' OR LOWER(a.nombre) LIKE '%auditoria%' OR LOWER(a.nombre) LIKE '%programa de auditor%'
A62: control_interno | B62: actividad_plan_anual_5 | C62: nombre | D62: control_interno.v_estado_vinculacion_auditorias | E62: Vista
A63: control_interno | B63: actividad_plan_anual_5 | C63: fecha_inicio | D63: control_interno.v_estado_vinculacion_auditorias | E63: Vista
A64: control_interno | B64: actividad_plan_anual_5 | C64: estado | D64: control_interno.fn_actualizar_cumplimiento_auditorias_vigencia | E64: Función | F64: estado = CASE
A65: control_interno | B65: actividad_plan_anual_5 | C65: porcentaje_avance | D65: control_interno.fn_actualizar_cumplimiento_auditorias_vigencia | E65: Función | F65: porcentaje_avance = v_cumplimiento.porcentaje_cumplimiento,
A66: control_interno | B66: actividad_plan_anual_5 | C66: porcentaje_avance | D66: control_interno.v_estado_vinculacion_auditorias | E66: Vista
A67: control_interno | B67: actividad_plan_anual_5 | C67: total_auditorias_programadas | D67: control_interno.fn_actualizar_cumplimiento_auditorias_vigencia | E67: Función | F67: total_auditorias_programadas = v_cumplimiento.total_programadas,
A68: control_interno | B68: actividad_plan_anual_5 | C68: total_auditorias_programadas | D68: control_interno.v_estado_vinculacion_auditorias | E68: Vista
A69: control_interno | B69: actividad_plan_anual_5 | C69: total_auditorias_finalizadas | D69: control_interno.fn_actualizar_cumplimiento_auditorias_vigencia | E69: Función | F69: total_auditorias_finalizadas = v_cumplimiento.total_finalizadas,
A70: control_interno | B70: actividad_plan_anual_5 | C70: total_auditorias_finalizadas | D70: control_interno.v_estado_vinculacion_auditorias | E70: Vista
A71: control_interno | B71: actividad_proceso_auditoria | C71: fase | D71: control_interno.actualizar_actividades_auditoria | E71: Función | F71: -- Obtener la fase actual de la auditoría -- Si no hay fase, salir -- Contar actividades de la fase actual de la auditoría
A72: control_interno | B72: actividad_proceso_auditoria | C72: estado | D72: control_interno.actualizar_actividades_auditoria | E72: Función | F72: SELECT COUNT(*), COUNT(*) FILTER (WHERE estado = 'completada')
A73: control_interno | B73: actividad_proceso_auditoria | C73: estado | D73: trigger_actualizar_actividades | E73: Trigger (UPDATE OF)
A74: control_interno | B74: aprobacion | C74: estado | D74: control_interno.trigger_evento_actualizacion_plan | E74: Función | F74: -- Solo registrar si cambió el estado IF OLD.estado IS DISTINCT FROM NEW.estado THEN WHEN NEW.estado = 'aprobado' THEN 'APROBACION'::control_interno.tipo_evento_timeline
A75: control_interno | B75: aprobacion | C75: aprobado_por | D75: control_interno.trigger_evento_actualizacion_plan | E75: Función | F75: COALESCE(NEW.aprobado_por, NEW.responsable_implementacion), -- usar aprobado_por si es aprobación, sino responsable_implementacion
A76: control_interno | B76: auditor_perfil | C76: cargo | D76: control_interno.v_auditor_disponibilidad | E76: Vista
A77: control_interno | B77: auditor_perfil | C77: cargo | D77: control_interno.v_auditorias_kanban_completo | E77: Vista
A78: control_interno | B78: auditor_perfil | C78: nivel_experiencia | D78: control_interno.v_auditor_disponibilidad | E78: Vista
A79: control_interno | B79: auditor_perfil | C79: fecha_ultima_actividad | D79: control_interno.v_auditor_disponibilidad | E79: Vista
A80: control_interno | B80: auditor_perfil | C80: observaciones | D80: control_interno.v_auditor_disponibilidad | E80: Vista
A81: control_interno | B81: auditor_perfil | C81: activo | D81: control_interno.v_auditor_disponibilidad | E81: Vista
A82: control_interno | B82: auditor_perfil | C82: activo | D82: control_interno.v_auditorias_kanban_completo | E82: Vista
A83: control_interno | B83: auditoria | C83: codigo | D83: control_interno.v_auditorias_finalizadas | E83: Vista
A84: control_interno | B84: auditoria | C84: codigo | D84: control_interno.v_auditorias_kanban_completo | E84: Vista
A85: control_interno | B85: auditoria | C85: nombre | D85: control_interno.fn_configurar_actividad_auditorias_plan | E85: Función | F85: LOWER(a.nombre) LIKE '%auditoría%' OR LOWER(a.nombre) LIKE '%auditoria%' OR LOWER(a.nombre) LIKE '%programa de auditor%'
A86: control_interno | B86: auditoria | C86: nombre | D86: control_interno.v_auditor_disponibilidad | E86: Vista
A87: control_interno | B87: auditoria | C87: nombre | D87: control_interno.v_auditorias_finalizadas | E87: Vista
A88: control_interno | B88: auditoria | C88: nombre | D88: control_interno.v_auditorias_kanban_completo | E88: Vista
A89: control_interno | B89: auditoria | C89: nombre | D89: control_interno.v_estado_vinculacion_auditorias | E89: Vista
A90: control_interno | B90: auditoria | C90: tipo | D90: control_interno.actualizar_contadores_documentos_informes | E90: Función | F90: -- Determinar el ID de la auditoría y el tipo de documento -- Determinar si es un informe basado en el tipo de documento
A91: control_interno | B91: auditoria | C91: tipo | D91: control_interno.fn_calcular_cumplimiento_auditorias | E91: Función | F91: COALESCE(tipo, 'regular') AS tipo_grupo, GROUP BY COALESCE(tipo, 'regular')
A92: control_interno | B92: auditoria | C92: tipo | D92: control_interno.v_auditorias_finalizadas | E92: Vista
A93: control_interno | B93: auditoria | C93: tipo | D93: control_interno.v_auditorias_kanban_completo | E93: Vista
A94: control_interno | B94: auditoria | C94: tipo | D94: control_interno.v_resumen_auditorias_por_año | E94: Vista
A95: control_interno | B95: auditoria | C95: territorial | D95: control_interno.v_auditorias_kanban_completo | E95: Vista
A96: control_interno | B96: auditoria | C96: progreso | D96: control_interno.v_auditorias_finalizadas | E96: Vista
A97: control_interno | B97: auditoria | C97: progreso | D97: control_interno.v_auditorias_kanban_completo | E97: Vista
A98: control_interno | B98: auditoria | C98: progreso | D98: control_interno.v_auditorias_por_estado | E98: Vista
A99: control_interno | B99: auditoria | C99: prioridad | D99: control_interno.v_auditorias_kanban_completo | E99: Vista
A100: control_interno | B100: auditoria | C100: hallazgos | D100: control_interno.v_auditorias_finalizadas | E100: Vista
A101: control_interno | B101: auditoria | C101: hallazgos | D101: control_interno.v_auditorias_kanban_completo | E101: Vista
...
